{
"meta":{"test_sets":[],"test_metrics":[],"learn_metrics":[{"best_value":"Min","name":"Logloss"}],"launch_mode":"Train","parameters":"","iteration_count":1000,"learn_sets":["learn"],"name":"experiment"},
"iterations":[
{"learn":[0.6450821307],"iteration":0,"passed_time":0.01616499516,"remaining_time":16.14883016},
{"learn":[0.5925462211],"iteration":1,"passed_time":0.030413183,"remaining_time":15.17617832},
{"learn":[0.5555801407],"iteration":2,"passed_time":0.04696236684,"remaining_time":15.60715991},
{"learn":[0.5169815588],"iteration":3,"passed_time":0.05883891525,"remaining_time":14.6508899},
{"learn":[0.4836963982],"iteration":4,"passed_time":0.06797702892,"remaining_time":13.52742876},
{"learn":[0.4575144915],"iteration":5,"passed_time":0.08288959945,"remaining_time":13.73204364},
{"learn":[0.4347614579],"iteration":6,"passed_time":0.1007995817,"remaining_time":14.29914066},
{"learn":[0.4119422408],"iteration":7,"passed_time":0.1139819563,"remaining_time":14.13376258},
{"learn":[0.3906999649],"iteration":8,"passed_time":0.131421026,"remaining_time":14.4709152},
{"learn":[0.3749202595],"iteration":9,"passed_time":0.143569046,"remaining_time":14.21333555},
{"learn":[0.3606146088],"iteration":10,"passed_time":0.1648758606,"remaining_time":14.82383874},
{"learn":[0.3492863099],"iteration":11,"passed_time":0.1742179606,"remaining_time":14.34394542},
{"learn":[0.3363563226],"iteration":12,"passed_time":0.1918257228,"remaining_time":14.56399911},
{"learn":[0.3253964393],"iteration":13,"passed_time":0.209168028,"remaining_time":14.7314054},
{"learn":[0.3158455482],"iteration":14,"passed_time":0.2258462193,"remaining_time":14.8305684},
{"learn":[0.3073909959],"iteration":15,"passed_time":0.2462172907,"remaining_time":15.14236338},
{"learn":[0.300396596],"iteration":16,"passed_time":0.2577305208,"remaining_time":14.90288835},
{"learn":[0.2945916203],"iteration":17,"passed_time":0.2828892671,"remaining_time":15.43318113},
{"learn":[0.2878663362],"iteration":18,"passed_time":0.2924517185,"remaining_time":15.09974399},
{"learn":[0.2833669944],"iteration":19,"passed_time":0.3084423738,"remaining_time":15.11367631},
{"learn":[0.278534831],"iteration":20,"passed_time":0.3232280351,"remaining_time":15.06858316},
{"learn":[0.2746983189],"iteration":21,"passed_time":0.3474709586,"remaining_time":15.44666352},
{"learn":[0.2699074933],"iteration":22,"passed_time":0.3583447152,"remaining_time":15.22186029},
{"learn":[0.2656742281],"iteration":23,"passed_time":0.3716147583,"remaining_time":15.11233351},
{"learn":[0.2628561011],"iteration":24,"passed_time":0.3921547153,"remaining_time":15.2940339},
{"learn":[0.260480951],"iteration":25,"passed_time":0.4044521244,"remaining_time":15.15139881},
{"learn":[0.2581528876],"iteration":26,"passed_time":0.4159568598,"remaining_time":14.98985276},
{"learn":[0.2555180881],"iteration":27,"passed_time":0.4371264789,"remaining_time":15.17453348},
{"learn":[0.2526686114],"iteration":28,"passed_time":0.4534007442,"remaining_time":15.18110768},
{"learn":[0.2507600652],"iteration":29,"passed_time":0.4720654315,"remaining_time":15.26344895},
{"learn":[0.2487109165],"iteration":30,"passed_time":0.489096922,"remaining_time":15.28822314},
{"learn":[0.2471984762],"iteration":31,"passed_time":0.5114328027,"remaining_time":15.47084228},
{"learn":[0.2461283524],"iteration":32,"passed_time":0.5238235367,"remaining_time":15.34961697},
{"learn":[0.2444772484],"iteration":33,"passed_time":0.5435314347,"remaining_time":15.44268723},
{"learn":[0.2429570985],"iteration":34,"passed_time":0.5537346599,"remaining_time":15.26725562},
{"learn":[0.2419312492],"iteration":35,"passed_time":0.5678329247,"remaining_time":15.20530387},
{"learn":[0.240835436],"iteration":36,"passed_time":0.5881783452,"remaining_time":15.30853369},
{"learn":[0.2395801421],"iteration":37,"passed_time":0.6010921819,"remaining_time":15.21712313},
{"learn":[0.2384578047],"iteration":38,"passed_time":0.6181403846,"remaining_time":15.23161307},
{"learn":[0.2365884938],"iteration":39,"passed_time":0.6344757576,"remaining_time":15.22741818},
{"learn":[0.2353382979],"iteration":40,"passed_time":0.6470786717,"remaining_time":15.13532796},
{"learn":[0.2345898107],"iteration":41,"passed_time":0.6582020153,"remaining_time":15.01327454},
{"learn":[0.2336174746],"iteration":42,"passed_time":0.6777683487,"remaining_time":15.08428627},
{"learn":[0.2323014834],"iteration":43,"passed_time":0.6882574305,"remaining_time":14.9539569},
{"learn":[0.2315498188],"iteration":44,"passed_time":0.7006618826,"remaining_time":14.86960218},
{"learn":[0.2301323533],"iteration":45,"passed_time":0.7141356023,"remaining_time":14.8105514},
{"learn":[0.2293140399],"iteration":46,"passed_time":0.7260678357,"remaining_time":14.72218399},
{"learn":[0.228455745],"iteration":47,"passed_time":0.7470906427,"remaining_time":14.81729775},
{"learn":[0.2276835637],"iteration":48,"passed_time":0.7587392677,"remaining_time":14.72573558},
{"learn":[0.2270714771],"iteration":49,"passed_time":0.7709795105,"remaining_time":14.6486107},
{"learn":[0.2264819925],"iteration":50,"passed_time":0.7882658577,"remaining_time":14.66792743},
{"learn":[0.2258122265],"iteration":51,"passed_time":0.7998249594,"remaining_time":14.58142426},
{"learn":[0.2252658268],"iteration":52,"passed_time":0.8146168625,"remaining_time":14.55551262},
{"learn":[0.2245829282],"iteration":53,"passed_time":0.8317345624,"remaining_time":14.57075733},
{"learn":[0.2240700822],"iteration":54,"passed_time":0.8521316544,"remaining_time":14.64117115},
{"learn":[0.2235586185],"iteration":55,"passed_time":0.8711589042,"remaining_time":14.6852501},
{"learn":[0.2229859175],"iteration":56,"passed_time":0.8801173326,"remaining_time":14.56053762},
{"learn":[0.2224122533],"iteration":57,"passed_time":0.894029067,"remaining_time":14.52026519},
{"learn":[0.2219220557],"iteration":58,"passed_time":0.9092523975,"remaining_time":14.50180519},
{"learn":[0.2215268774],"iteration":59,"passed_time":0.9288254818,"remaining_time":14.55159922},
{"learn":[0.2212724986],"iteration":60,"passed_time":0.9487192795,"remaining_time":14.60405579},
{"learn":[0.2208570826],"iteration":61,"passed_time":0.958218447,"remaining_time":14.49691779},
{"learn":[0.2201426616],"iteration":62,"passed_time":0.9809501451,"remaining_time":14.58968708},
{"learn":[0.2198707651],"iteration":63,"passed_time":0.9901445276,"remaining_time":14.48086372},
{"learn":[0.2194372741],"iteration":64,"passed_time":1.004003572,"remaining_time":14.44220523},
{"learn":[0.2189543956],"iteration":65,"passed_time":1.015199407,"remaining_time":14.36660978},
{"learn":[0.218524434],"iteration":66,"passed_time":1.033492622,"remaining_time":14.39177039},
{"learn":[0.2181830022],"iteration":67,"passed_time":1.055419546,"remaining_time":14.46545612},
{"learn":[0.2179495124],"iteration":68,"passed_time":1.07040269,"remaining_time":14.44267977},
{"learn":[0.2177326999],"iteration":69,"passed_time":1.086489143,"remaining_time":14.43478433},
{"learn":[0.2174469951],"iteration":70,"passed_time":1.100464576,"remaining_time":14.39903649},
{"learn":[0.2171850132],"iteration":71,"passed_time":1.116803935,"remaining_time":14.39436182},
{"learn":[0.2168712562],"iteration":72,"passed_time":1.128997605,"remaining_time":14.33672301},
{"learn":[0.2166625701],"iteration":73,"passed_time":1.139890055,"remaining_time":14.26402961},
{"learn":[0.2164555709],"iteration":74,"passed_time":1.156799232,"remaining_time":14.26719053},
{"learn":[0.2162457902],"iteration":75,"passed_time":1.171939821,"remaining_time":14.24832098},
{"learn":[0.2159674051],"iteration":76,"passed_time":1.184495991,"remaining_time":14.19856882},
{"learn":[0.2157277596],"iteration":77,"passed_time":1.199524092,"remaining_time":14.17898991},
{"learn":[0.2155100804],"iteration":78,"passed_time":1.212778285,"remaining_time":14.13884557},
{"learn":[0.215287905],"iteration":79,"passed_time":1.224109654,"remaining_time":14.07726102},
{"learn":[0.2151472871],"iteration":80,"passed_time":1.233579418,"remaining_time":13.99579611},
{"learn":[0.2145797546],"iteration":81,"passed_time":1.255756172,"remaining_time":14.05834349},
{"learn":[0.21435802],"iteration":82,"passed_time":1.265489008,"remaining_time":13.98136651},
{"learn":[0.2140044819],"iteration":83,"passed_time":1.281943577,"remaining_time":13.97928949},
{"learn":[0.2138681366],"iteration":84,"passed_time":1.29915177,"remaining_time":13.9849867},
{"learn":[0.2133965374],"iteration":85,"passed_time":1.317065833,"remaining_time":13.99765316},
{"learn":[0.2132054095],"iteration":86,"passed_time":1.335517981,"remaining_time":14.01526341},
{"learn":[0.2130193032],"iteration":87,"passed_time":1.346795886,"remaining_time":13.95770281},
{"learn":[0.2127399867],"iteration":88,"passed_time":1.367742097,"remaining_time":14.00014664},
{"learn":[0.2126193523],"iteration":89,"passed_time":1.378395269,"remaining_time":13.93710772},
{"learn":[0.212430998],"iteration":90,"passed_time":1.390234991,"remaining_time":13.8870726},
{"learn":[0.212122556],"iteration":91,"passed_time":1.410886,"remaining_time":13.92483139},
{"learn":[0.2120067504],"iteration":92,"passed_time":1.428654454,"remaining_time":13.93322139},
{"learn":[0.2118114754],"iteration":93,"passed_time":1.452867469,"remaining_time":14.00316943},
{"learn":[0.2116604919],"iteration":94,"passed_time":1.472671328,"remaining_time":14.02913213},
{"learn":[0.2115665729],"iteration":95,"passed_time":1.49200956,"remaining_time":14.04975669},
{"learn":[0.2114312955],"iteration":96,"passed_time":1.511166948,"remaining_time":14.06787376},
{"learn":[0.2112850108],"iteration":97,"passed_time":1.529553015,"remaining_time":14.07813081},
{"learn":[0.2111168891],"iteration":98,"passed_time":1.549171961,"remaining_time":14.09902967},
{"learn":[0.2109726332],"iteration":99,"passed_time":1.591101673,"remaining_time":14.31991506},
{"learn":[0.2107576473],"iteration":100,"passed_time":1.628603314,"remaining_time":14.49618197},
{"learn":[0.2105444621],"iteration":101,"passed_time":1.661616647,"remaining_time":14.62874264},
{"learn":[0.2101466264],"iteration":102,"passed_time":1.683241198,"remaining_time":14.65890636},
{"learn":[0.2100011903],"iteration":103,"passed_time":1.709867981,"remaining_time":14.7311703},
{"learn":[0.20989837],"iteration":104,"passed_time":1.753425209,"remaining_time":14.9458625},
{"learn":[0.2094850848],"iteration":105,"passed_time":1.778686214,"remaining_time":15.00137241},
{"learn":[0.2092632624],"iteration":106,"passed_time":1.789407241,"remaining_time":14.93402492},
{"learn":[0.2091465352],"iteration":107,"passed_time":1.806064656,"remaining_time":14.91675623},
{"learn":[0.2088371125],"iteration":108,"passed_time":1.821276993,"remaining_time":14.88768625},
{"learn":[0.2087257058],"iteration":109,"passed_time":1.835698145,"remaining_time":14.85246681},
{"learn":[0.2085653405],"iteration":110,"passed_time":1.856228162,"remaining_time":14.86654807},
{"learn":[0.2084506152],"iteration":111,"passed_time":1.87202603,"remaining_time":14.84249209},
{"learn":[0.2083058393],"iteration":112,"passed_time":1.889168086,"remaining_time":14.82913356},
{"learn":[0.208090914],"iteration":113,"passed_time":1.905862119,"remaining_time":14.81222664},
{"learn":[0.2077631458],"iteration":114,"passed_time":1.917340207,"remaining_time":14.75518333},
{"learn":[0.2074552931],"iteration":115,"passed_time":1.93685289,"remaining_time":14.76015478},
{"learn":[0.20722827],"iteration":116,"passed_time":1.949862093,"remaining_time":14.71562588},
{"learn":[0.207093377],"iteration":117,"passed_time":1.962765652,"remaining_time":14.67084157},
{"learn":[0.2068705797],"iteration":118,"passed_time":1.983453171,"remaining_time":14.68422054},
{"learn":[0.2067494608],"iteration":119,"passed_time":2.000243199,"remaining_time":14.66845013},
{"learn":[0.2065926618],"iteration":120,"passed_time":2.014889324,"remaining_time":14.63708856},
{"learn":[0.2064798426],"iteration":121,"passed_time":2.030207138,"remaining_time":14.61083498},
{"learn":[0.2063441511],"iteration":122,"passed_time":2.039927535,"remaining_time":14.54484917},
{"learn":[0.2060826574],"iteration":123,"passed_time":2.059896858,"remaining_time":14.55217457},
{"learn":[0.2059066428],"iteration":124,"passed_time":2.069171335,"remaining_time":14.48419934},
{"learn":[0.2058290025],"iteration":125,"passed_time":2.081395291,"remaining_time":14.43761495},
{"learn":[0.2056123444],"iteration":126,"passed_time":2.101860792,"remaining_time":14.44822419},
{"learn":[0.2054767509],"iteration":127,"passed_time":2.112961784,"remaining_time":14.39455215},
{"learn":[0.2053559245],"iteration":128,"passed_time":2.12889474,"remaining_time":14.37416526},
{"learn":[0.2051934147],"iteration":129,"passed_time":2.146420364,"remaining_time":14.36450551},
{"learn":[0.2050504375],"iteration":130,"passed_time":2.161669735,"remaining_time":14.33962595},
{"learn":[0.2048746474],"iteration":131,"passed_time":2.173197384,"remaining_time":14.29041916},
{"learn":[0.2047990168],"iteration":132,"passed_time":2.188120637,"remaining_time":14.26391423},
{"learn":[0.204701387],"iteration":133,"passed_time":2.197670684,"remaining_time":14.20285681},
{"learn":[0.2045818567],"iteration":134,"passed_time":2.221039241,"remaining_time":14.23110329},
{"learn":[0.2044723604],"iteration":135,"passed_time":2.230309209,"remaining_time":14.16902321},
{"learn":[0.2043020985],"iteration":136,"passed_time":2.247584287,"remaining_time":14.15814044},
{"learn":[0.2041787984],"iteration":137,"passed_time":2.264577255,"remaining_time":14.14540285},
{"learn":[0.204098952],"iteration":138,"passed_time":2.28665105,"remaining_time":14.16407593},
{"learn":[0.2039437847],"iteration":139,"passed_time":2.298248672,"remaining_time":14.11781327},
{"learn":[0.2038668498],"iteration":140,"passed_time":2.309690922,"remaining_time":14.07109576},
{"learn":[0.2036757505],"iteration":141,"passed_time":2.328274175,"remaining_time":14.06802283},
{"learn":[0.2034643072],"iteration":142,"passed_time":2.344930474,"remaining_time":14.05318473},
{"learn":[0.2031929798],"iteration":143,"passed_time":2.362330883,"remaining_time":14.04274469},
{"learn":[0.2031165404],"iteration":144,"passed_time":2.377063388,"remaining_time":14.01647722},
{"learn":[0.203101836],"iteration":145,"passed_time":2.385945002,"remaining_time":13.95614405},
{"learn":[0.2030358348],"iteration":146,"passed_time":2.40675835,"remaining_time":13.96574743},
{"learn":[0.2028028764],"iteration":147,"passed_time":2.422253411,"remaining_time":13.94432369},
{"learn":[0.2027218933],"iteration":148,"passed_time":2.431359841,"remaining_time":13.88649144},
{"learn":[0.2026543012],"iteration":149,"passed_time":2.444473559,"remaining_time":13.85201683},
{"learn":[0.2024746364],"iteration":150,"passed_time":2.460841556,"remaining_time":13.83612239},
{"learn":[0.2023507142],"iteration":151,"passed_time":2.471819484,"remaining_time":13.79015081},
{"learn":[0.2022250548],"iteration":152,"passed_time":2.486823748,"remaining_time":13.76692624},
{"learn":[0.2020523633],"iteration":153,"passed_time":2.503103975,"remaining_time":13.75081794},
{"learn":[0.2019694614],"iteration":154,"passed_time":2.523593502,"remaining_time":13.7576549},
{"learn":[0.2018172688],"iteration":155,"passed_time":2.543068848,"remaining_time":13.75865454},
{"learn":[0.2017382156],"iteration":156,"passed_time":2.554204983,"remaining_time":13.71461657},
{"learn":[0.2016528874],"iteration":157,"passed_time":2.572970762,"remaining_time":13.71165431},
{"learn":[0.2015046464],"iteration":158,"passed_time":2.586379892,"remaining_time":13.68016031},
{"learn":[0.2014231858],"iteration":159,"passed_time":2.595584195,"remaining_time":13.62681702},
{"learn":[0.2013221424],"iteration":160,"passed_time":2.6187644,"remaining_time":13.64685299},
{"learn":[0.201217133],"iteration":161,"passed_time":2.635221652,"remaining_time":13.63157867},
{"learn":[0.201101013],"iteration":162,"passed_time":2.644495621,"remaining_time":13.5794039},
{"learn":[0.2010254005],"iteration":163,"passed_time":2.657916999,"remaining_time":13.54889397},
{"learn":[0.2009560726],"iteration":164,"passed_time":2.671177099,"remaining_time":13.51777502},
{"learn":[0.200815923],"iteration":165,"passed_time":2.689363282,"remaining_time":13.51162035},
{"learn":[0.2006756966],"iteration":166,"passed_time":2.707364724,"remaining_time":13.50440009},
{"learn":[0.2005219003],"iteration":167,"passed_time":2.720306928,"remaining_time":13.47199621},
{"learn":[0.2004630215],"iteration":168,"passed_time":2.737192305,"remaining_time":13.45921187},
{"learn":[0.2003468511],"iteration":169,"passed_time":2.754194319,"remaining_time":13.44694874},
{"learn":[0.2002249793],"iteration":170,"passed_time":2.773051071,"remaining_time":13.44362186},
{"learn":[0.2001657219],"iteration":171,"passed_time":2.78343296,"remaining_time":13.39931681},
{"learn":[0.2000257772],"iteration":172,"passed_time":2.802295925,"remaining_time":13.39594642},
{"learn":[0.1999753463],"iteration":173,"passed_time":2.816560933,"remaining_time":13.37057087},
{"learn":[0.1999202323],"iteration":174,"passed_time":2.835480064,"remaining_time":13.36726316},
{"learn":[0.1998199335],"iteration":175,"passed_time":2.851904679,"remaining_time":13.35209918},
{"learn":[0.1997103286],"iteration":176,"passed_time":2.865635659,"remaining_time":13.32439631},
{"learn":[0.1996252221],"iteration":177,"passed_time":2.878389659,"remaining_time":13.29233876},
{"learn":[0.1995526407],"iteration":178,"passed_time":2.889633713,"remaining_time":13.25357139},
{"learn":[0.199474402],"iteration":179,"passed_time":2.899059462,"remaining_time":13.20682644},
{"learn":[0.199406868],"iteration":180,"passed_time":2.918141245,"remaining_time":13.20418608},
{"learn":[0.1993010597],"iteration":181,"passed_time":2.929974936,"remaining_time":13.16878845},
{"learn":[0.1992703985],"iteration":182,"passed_time":2.936807364,"remaining_time":13.11132031},
{"learn":[0.1990577555],"iteration":183,"passed_time":2.950788381,"remaining_time":13.08610499},
{"learn":[0.1990330809],"iteration":184,"passed_time":2.965783635,"remaining_time":13.06547926},
{"learn":[0.1988875057],"iteration":185,"passed_time":2.982147631,"remaining_time":13.05090415},
{"learn":[0.1987468694],"iteration":186,"passed_time":2.997937365,"remaining_time":13.03381325},
{"learn":[0.19864539],"iteration":187,"passed_time":3.01601948,"remaining_time":13.02663733},
{"learn":[0.1985984688],"iteration":188,"passed_time":3.030146735,"remaining_time":13.00237567},
{"learn":[0.1985051664],"iteration":189,"passed_time":3.047427571,"remaining_time":12.99166491},
{"learn":[0.1984255921],"iteration":190,"passed_time":3.063144604,"remaining_time":12.9742617},
{"learn":[0.1983621929],"iteration":191,"passed_time":3.079566557,"remaining_time":12.95984259},
{"learn":[0.1982390537],"iteration":192,"passed_time":3.096091117,"remaining_time":12.94583177},
{"learn":[0.1981453504],"iteration":193,"passed_time":3.109507459,"remaining_time":12.9188815},
{"learn":[0.1980136466],"iteration":194,"passed_time":3.136157944,"remaining_time":12.94670331},
{"learn":[0.197941109],"iteration":195,"passed_time":3.147618181,"remaining_time":12.91165825},
{"learn":[0.1979076934],"iteration":196,"passed_time":3.159044912,"remaining_time":12.87671606},
{"learn":[0.1978699887],"iteration":197,"passed_time":3.176237867,"remaining_time":12.86536752},
{"learn":[0.1977533799],"iteration":198,"passed_time":3.191480919,"remaining_time":12.84611164},
{"learn":[0.1975928287],"iteration":199,"passed_time":3.204412601,"remaining_time":12.8176504},
{"learn":[0.1975072733],"iteration":200,"passed_time":3.214482288,"remaining_time":12.77796691},
{"learn":[0.1972678356],"iteration":201,"passed_time":3.231958521,"remaining_time":12.76783614},
{"learn":[0.1972017735],"iteration":202,"passed_time":3.245309034,"remaining_time":12.74143498},
{"learn":[0.197126332],"iteration":203,"passed_time":3.268254894,"remaining_time":12.75260243},
{"learn":[0.1970968772],"iteration":204,"passed_time":3.277056351,"remaining_time":12.70858439},
{"learn":[0.1970280367],"iteration":205,"passed_time":3.288269283,"remaining_time":12.67420296},
{"learn":[0.1968224209],"iteration":206,"passed_time":3.305259551,"remaining_time":12.66217789},
{"learn":[0.1967543032],"iteration":207,"passed_time":3.318429565,"remaining_time":12.63555873},
{"learn":[0.1966189907],"iteration":208,"passed_time":3.330606359,"remaining_time":12.60530923},
{"learn":[0.1965768227],"iteration":209,"passed_time":3.341653793,"remaining_time":12.57098332},
{"learn":[0.196456836],"iteration":210,"passed_time":3.358502276,"remaining_time":12.55857012},
{"learn":[0.1964001767],"iteration":211,"passed_time":3.370483409,"remaining_time":12.52802324},
{"learn":[0.1962777147],"iteration":212,"passed_time":3.391220338,"remaining_time":12.53000191},
{"learn":[0.1961084793],"iteration":213,"passed_time":3.403718601,"remaining_time":12.50150851},
{"learn":[0.1960531657],"iteration":214,"passed_time":3.421175352,"remaining_time":12.49126815},
{"learn":[0.1959986626],"iteration":215,"passed_time":3.437554129,"remaining_time":12.47704832},
{"learn":[0.1958225595],"iteration":216,"passed_time":3.452980083,"remaining_time":12.45937053},
{"learn":[0.1957300735],"iteration":217,"passed_time":3.468460131,"remaining_time":12.44190744},
{"learn":[0.1956756697],"iteration":218,"passed_time":3.480977728,"remaining_time":12.41389774},
{"learn":[0.1955556372],"iteration":219,"passed_time":3.490024436,"remaining_time":12.373723},
{"learn":[0.1954000162],"iteration":220,"passed_time":3.513472902,"remaining_time":12.38459453},
{"learn":[0.1953126947],"iteration":221,"passed_time":3.522039012,"remaining_time":12.34300158},
{"learn":[0.1951812946],"iteration":222,"passed_time":3.537528699,"remaining_time":12.32582869},
{"learn":[0.1951441274],"iteration":223,"passed_time":3.55309022,"remaining_time":12.30891969},
{"learn":[0.1949792824],"iteration":224,"passed_time":3.568662209,"remaining_time":12.29205872},
{"learn":[0.1949175216],"iteration":225,"passed_time":3.588207603,"remaining_time":12.28881719},
{"learn":[0.1948688452],"iteration":226,"passed_time":3.604565102,"remaining_time":12.27457632},
{"learn":[0.1947920953],"iteration":227,"passed_time":3.619624225,"remaining_time":12.25592062},
{"learn":[0.1946112395],"iteration":228,"passed_time":3.632283839,"remaining_time":12.22921764},
{"learn":[0.194457544],"iteration":229,"passed_time":3.652029583,"remaining_time":12.22635991},
{"learn":[0.1943753531],"iteration":230,"passed_time":3.66327074,"remaining_time":12.19504415},
{"learn":[0.194296687],"iteration":231,"passed_time":3.674470062,"remaining_time":12.16376297},
{"learn":[0.1942229476],"iteration":232,"passed_time":3.683626568,"remaining_time":12.12592952},
{"learn":[0.1941605094],"iteration":233,"passed_time":3.70729215,"remaining_time":12.1358367},
{"learn":[0.1940868958],"iteration":234,"passed_time":3.717695994,"remaining_time":12.10228696},
{"learn":[0.1940055235],"iteration":235,"passed_time":3.734011953,"remaining_time":12.08807259},
{"learn":[0.1939084305],"iteration":236,"passed_time":3.749552813,"remaining_time":12.07134513},
{"learn":[0.1938157902],"iteration":237,"passed_time":3.76272519,"remaining_time":12.04704452},
{"learn":[0.1937530006],"iteration":238,"passed_time":3.785057278,"remaining_time":12.05200246},
{"learn":[0.1935425453],"iteration":239,"passed_time":3.800115823,"remaining_time":12.0337001},
{"learn":[0.1934566606],"iteration":240,"passed_time":3.811940451,"remaining_time":12.00523984},
{"learn":[0.1934090153],"iteration":241,"passed_time":3.83219475,"remaining_time":12.00332075},
{"learn":[0.1932427187],"iteration":242,"passed_time":3.844905099,"remaining_time":11.97774963},
{"learn":[0.1931457637],"iteration":243,"passed_time":3.86417589,"remaining_time":11.97261054},
{"learn":[0.19307129],"iteration":244,"passed_time":3.882531748,"remaining_time":11.96453661},
{"learn":[0.1930202224],"iteration":245,"passed_time":3.892652253,"remaining_time":11.93113739},
{"learn":[0.1929007723],"iteration":246,"passed_time":3.912975542,"remaining_time":11.9290307},
{"learn":[0.1927991496],"iteration":247,"passed_time":3.926318977,"remaining_time":11.90561238},
{"learn":[0.1927260338],"iteration":248,"passed_time":3.942472761,"remaining_time":11.89075118},
{"learn":[0.192624965],"iteration":249,"passed_time":3.953742055,"remaining_time":11.86122616},
{"learn":[0.1925888401],"iteration":250,"passed_time":3.971191436,"remaining_time":11.85028839},
{"learn":[0.1925609415],"iteration":251,"passed_time":3.986930501,"remaining_time":11.83422228},
{"learn":[0.1924725177],"iteration":252,"passed_time":3.997806782,"remaining_time":11.80380105},
{"learn":[0.1924125143],"iteration":253,"passed_time":4.007840014,"remaining_time":11.77105768},
{"learn":[0.1923558713],"iteration":254,"passed_time":4.032973234,"remaining_time":11.78260808},
{"learn":[0.1922168663],"iteration":255,"passed_time":4.042180251,"remaining_time":11.74758635},
{"learn":[0.1920017965],"iteration":256,"passed_time":4.05383506,"remaining_time":11.71984222},
{"learn":[0.1919438352],"iteration":257,"passed_time":4.077235039,"remaining_time":11.72600155},
{"learn":[0.1917498405],"iteration":258,"passed_time":4.088318337,"remaining_time":11.69669455},
{"learn":[0.1916776183],"iteration":259,"passed_time":4.102570572,"remaining_time":11.67654701},
{"learn":[0.191575372],"iteration":260,"passed_time":4.117996868,"remaining_time":11.65976891},
{"learn":[0.1914977715],"iteration":261,"passed_time":4.131435356,"remaining_time":11.63740188},
{"learn":[0.1914284649],"iteration":262,"passed_time":4.143476586,"remaining_time":11.61118724},
{"learn":[0.191270123],"iteration":263,"passed_time":4.16195346,"remaining_time":11.60302177},
{"learn":[0.1912304641],"iteration":264,"passed_time":4.182549706,"remaining_time":11.60065673},
{"learn":[0.1911008293],"iteration":265,"passed_time":4.199786826,"remaining_time":11.58888545},
{"learn":[0.1910276576],"iteration":266,"passed_time":4.208779826,"remaining_time":11.5544405},
{"learn":[0.1908851307],"iteration":267,"passed_time":4.229064,"remaining_time":11.55102555},
{"learn":[0.190836559],"iteration":268,"passed_time":4.245113572,"remaining_time":11.53597777},
{"learn":[0.190803025],"iteration":269,"passed_time":4.258957995,"remaining_time":11.51496051},
{"learn":[0.1907629169],"iteration":270,"passed_time":4.279278793,"remaining_time":11.51141786},
{"learn":[0.190717986],"iteration":271,"passed_time":4.288278497,"remaining_time":11.47745127},
{"learn":[0.1906027507],"iteration":272,"passed_time":4.312579325,"remaining_time":11.48441454},
{"learn":[0.1905435081],"iteration":273,"passed_time":4.321045184,"remaining_time":11.44919271},
{"learn":[0.1903877218],"iteration":274,"passed_time":4.334074462,"remaining_time":11.42619631},
{"learn":[0.1902716485],"iteration":275,"passed_time":4.354634405,"remaining_time":11.42302648},
{"learn":[0.1902190001],"iteration":276,"passed_time":4.368499818,"remaining_time":11.40225765},
{"learn":[0.1901571519],"iteration":277,"passed_time":4.38276948,"remaining_time":11.38258836},
{"learn":[0.190085195],"iteration":278,"passed_time":4.402164157,"remaining_time":11.376202},
{"learn":[0.1899954846],"iteration":279,"passed_time":4.416962887,"remaining_time":11.35790457},
{"learn":[0.1899056306],"iteration":280,"passed_time":4.436008535,"remaining_time":11.35049871},
{"learn":[0.1898285665],"iteration":281,"passed_time":4.450017147,"remaining_time":11.3301855},
{"learn":[0.1897795167],"iteration":282,"passed_time":4.462350079,"remaining_time":11.3056714},
{"learn":[0.1896950466],"iteration":283,"passed_time":4.476658269,"remaining_time":11.28622296},
{"learn":[0.189587449],"iteration":284,"passed_time":4.495993186,"remaining_time":11.2794215},
{"learn":[0.1895389388],"iteration":285,"passed_time":4.511943699,"remaining_time":11.26408322},
{"learn":[0.1894957078],"iteration":286,"passed_time":4.528226142,"remaining_time":11.24956529},
{"learn":[0.1894400519],"iteration":287,"passed_time":4.541281378,"remaining_time":11.22705674},
{"learn":[0.1893677364],"iteration":288,"passed_time":4.550295899,"remaining_time":11.19467261},
{"learn":[0.1892433782],"iteration":289,"passed_time":4.577911485,"remaining_time":11.20799019},
{"learn":[0.1891832935],"iteration":290,"passed_time":4.59387101,"remaining_time":11.19262731},
{"learn":[0.189059576],"iteration":291,"passed_time":4.607707584,"remaining_time":11.17211291},
{"learn":[0.1889282435],"iteration":292,"passed_time":4.618266436,"remaining_time":11.14373505},
{"learn":[0.1888183178],"iteration":293,"passed_time":4.62896982,"remaining_time":11.11582549},
{"learn":[0.1886648992],"iteration":294,"passed_time":4.649979845,"remaining_time":11.1126637},
{"learn":[0.1886121652],"iteration":295,"passed_time":4.659801833,"remaining_time":11.08277193},
{"learn":[0.1885341394],"iteration":296,"passed_time":4.676707268,"remaining_time":11.06978185},
{"learn":[0.1884125367],"iteration":297,"passed_time":4.68923921,"remaining_time":11.04646284},
{"learn":[0.1883260935],"iteration":298,"passed_time":4.706119356,"remaining_time":11.03341026},
{"learn":[0.1882801358],"iteration":299,"passed_time":4.714535335,"remaining_time":11.00058245},
{"learn":[0.1882086783],"iteration":300,"passed_time":4.735988077,"remaining_time":10.99819158},
{"learn":[0.1882005621],"iteration":301,"passed_time":4.744698261,"remaining_time":10.96622313},
{"learn":[0.188127395],"iteration":302,"passed_time":4.754861399,"remaining_time":10.93775048},
{"learn":[0.1880492496],"iteration":303,"passed_time":4.763501083,"remaining_time":10.90591038},
{"learn":[0.1879631089],"iteration":304,"passed_time":4.789304123,"remaining_time":10.91333235},
{"learn":[0.1879538413],"iteration":305,"passed_time":4.798367317,"remaining_time":10.88257163},
{"learn":[0.1878636931],"iteration":306,"passed_time":4.818151787,"remaining_time":10.87615371},
{"learn":[0.1878076576],"iteration":307,"passed_time":4.828333782,"remaining_time":10.8480746},
{"learn":[0.1877283133],"iteration":308,"passed_time":4.84485401,"remaining_time":10.83428518},
{"learn":[0.1876491065],"iteration":309,"passed_time":4.860621905,"remaining_time":10.81880359},
{"learn":[0.1875811558],"iteration":310,"passed_time":4.872219525,"remaining_time":10.7940812},
{"learn":[0.187540537],"iteration":311,"passed_time":4.892102487,"remaining_time":10.78771318},
{"learn":[0.1873925169],"iteration":312,"passed_time":4.904567733,"remaining_time":10.76497774},
{"learn":[0.1872784697],"iteration":313,"passed_time":4.92300299,"remaining_time":10.75535048},
{"learn":[0.1871803536],"iteration":314,"passed_time":4.93873573,"remaining_time":10.7397904},
{"learn":[0.1871211647],"iteration":315,"passed_time":4.950783126,"remaining_time":10.71625208},
{"learn":[0.1869524453],"iteration":316,"passed_time":4.961582201,"remaining_time":10.69009667},
{"learn":[0.1868808413],"iteration":317,"passed_time":4.983975859,"remaining_time":10.6889042},
{"learn":[0.1868740527],"iteration":318,"passed_time":4.993180239,"remaining_time":10.65942239},
{"learn":[0.186798991],"iteration":319,"passed_time":5.005844533,"remaining_time":10.63741963},
{"learn":[0.1867195061],"iteration":320,"passed_time":5.021658274,"remaining_time":10.62213697},
{"learn":[0.1865631636],"iteration":321,"passed_time":5.036243499,"remaining_time":10.60426426},
{"learn":[0.1864965101],"iteration":322,"passed_time":5.056792125,"remaining_time":10.59891105},
{"learn":[0.1864185683],"iteration":323,"passed_time":5.067455122,"remaining_time":10.57283847},
{"learn":[0.1863843106],"iteration":324,"passed_time":5.083955442,"remaining_time":10.55898438},
{"learn":[0.186317408],"iteration":325,"passed_time":5.097913086,"remaining_time":10.53985712},
{"learn":[0.1861844937],"iteration":326,"passed_time":5.108732942,"remaining_time":10.51430358},
{"learn":[0.1861243978],"iteration":327,"passed_time":5.132030194,"remaining_time":10.51440332},
{"learn":[0.1860628753],"iteration":328,"passed_time":5.148476073,"remaining_time":10.50038737},
{"learn":[0.185964507],"iteration":329,"passed_time":5.163013555,"remaining_time":10.48248207},
{"learn":[0.1858359646],"iteration":330,"passed_time":5.17203219,"remaining_time":10.4534427},
{"learn":[0.185748374],"iteration":331,"passed_time":5.185709286,"remaining_time":10.433897},
{"learn":[0.1856840514],"iteration":332,"passed_time":5.202534441,"remaining_time":10.42069211},
{"learn":[0.1856783515],"iteration":333,"passed_time":5.220578161,"remaining_time":10.40989537},
{"learn":[0.1855997817],"iteration":334,"passed_time":5.239277497,"remaining_time":10.40035682},
{"learn":[0.1854772994],"iteration":335,"passed_time":5.25307062,"remaining_time":10.38106813},
{"learn":[0.1854289521],"iteration":336,"passed_time":5.263946174,"remaining_time":10.35607215},
{"learn":[0.1854230801],"iteration":337,"passed_time":5.281615585,"remaining_time":10.34446603},
{"learn":[0.1854182338],"iteration":338,"passed_time":5.296725083,"remaining_time":10.32783268},
{"learn":[0.1853581469],"iteration":339,"passed_time":5.312593277,"remaining_time":10.31268107},
{"learn":[0.1853270672],"iteration":340,"passed_time":5.323925262,"remaining_time":10.28875879},
{"learn":[0.185321376],"iteration":341,"passed_time":5.345410756,"remaining_time":10.28444526},
{"learn":[0.1852800146],"iteration":342,"passed_time":5.361361697,"remaining_time":10.26943042},
{"learn":[0.1851937509],"iteration":343,"passed_time":5.379348843,"remaining_time":10.25829314},
{"learn":[0.1851217844],"iteration":344,"passed_time":5.399576275,"remaining_time":10.25136945},
{"learn":[0.185095211],"iteration":345,"passed_time":5.410519076,"remaining_time":10.22681929},
{"learn":[0.1850333318],"iteration":346,"passed_time":5.430008596,"remaining_time":10.21843116},
{"learn":[0.1849786446],"iteration":347,"passed_time":5.442780166,"remaining_time":10.19739273},
{"learn":[0.1849279229],"iteration":348,"passed_time":5.456736784,"remaining_time":10.17861217},
{"learn":[0.1848930517],"iteration":349,"passed_time":5.47878926,"remaining_time":10.17489434},
{"learn":[0.1848785922],"iteration":350,"passed_time":5.492463185,"remaining_time":10.15558008},
{"learn":[0.1848261554],"iteration":351,"passed_time":5.503666765,"remaining_time":10.13175018},
{"learn":[0.1848194254],"iteration":352,"passed_time":5.514051763,"remaining_time":10.10649147},
{"learn":[0.1847637637],"iteration":353,"passed_time":5.530910761,"remaining_time":10.09313094},
{"learn":[0.1847132797],"iteration":354,"passed_time":5.54143008,"remaining_time":10.06823212},
{"learn":[0.1846106753],"iteration":355,"passed_time":5.567116003,"remaining_time":10.0708503},
{"learn":[0.1845167923],"iteration":356,"passed_time":5.577057235,"remaining_time":10.04495183},
{"learn":[0.184400891],"iteration":357,"passed_time":5.594242582,"remaining_time":10.03213334},
{"learn":[0.1843434404],"iteration":358,"passed_time":5.608436765,"remaining_time":10.01394977},
{"learn":[0.1842710264],"iteration":359,"passed_time":5.625718015,"remaining_time":10.00127647},
{"learn":[0.1842216059],"iteration":360,"passed_time":5.643639357,"remaining_time":9.989710663},
{"learn":[0.1841953289],"iteration":361,"passed_time":5.653975657,"remaining_time":9.964741628},
{"learn":[0.1841452776],"iteration":362,"passed_time":5.675664777,"remaining_time":9.95977538},
{"learn":[0.1841056257],"iteration":363,"passed_time":5.687193804,"remaining_time":9.936964999},
{"learn":[0.1839683083],"iteration":364,"passed_time":5.703848508,"remaining_time":9.923133705},
{"learn":[0.1839032883],"iteration":365,"passed_time":5.715400377,"remaining_time":9.900447647},
{"learn":[0.1838561506],"iteration":366,"passed_time":5.727702298,"remaining_time":9.879115953},
{"learn":[0.1837674299],"iteration":367,"passed_time":5.750819377,"remaining_time":9.876407191},
{"learn":[0.1837343978],"iteration":368,"passed_time":5.769499204,"remaining_time":9.865999994},
{"learn":[0.1836989025],"iteration":369,"passed_time":5.780336709,"remaining_time":9.842194937},
{"learn":[0.1836340992],"iteration":370,"passed_time":5.791688512,"remaining_time":9.819331736},
{"learn":[0.1835372659],"iteration":371,"passed_time":5.807268551,"remaining_time":9.803668413},
{"learn":[0.1834307719],"iteration":372,"passed_time":5.82519931,"remaining_time":9.791957017},
{"learn":[0.1832950553],"iteration":373,"passed_time":5.840097314,"remaining_time":9.775136145},
{"learn":[0.1832382504],"iteration":374,"passed_time":5.853333784,"remaining_time":9.755556307},
{"learn":[0.1831912987],"iteration":375,"passed_time":5.875081482,"remaining_time":9.750135226},
{"learn":[0.183144861],"iteration":376,"passed_time":5.886686901,"remaining_time":9.727867213},
{"learn":[0.1830808197],"iteration":377,"passed_time":5.902976799,"remaining_time":9.713363938},
{"learn":[0.1830376111],"iteration":378,"passed_time":5.917195547,"remaining_time":9.695457611},
{"learn":[0.1829693598],"iteration":379,"passed_time":5.935600071,"remaining_time":9.684400116},
{"learn":[0.1828999207],"iteration":380,"passed_time":5.953851866,"remaining_time":9.673055918},
{"learn":[0.1828762692],"iteration":381,"passed_time":5.965537827,"remaining_time":9.651053343},
{"learn":[0.1828113383],"iteration":382,"passed_time":5.986256814,"remaining_time":9.643656538},
{"learn":[0.1827044524],"iteration":383,"passed_time":5.999494597,"remaining_time":9.624189249},
{"learn":[0.1826455643],"iteration":384,"passed_time":6.016087526,"remaining_time":9.610113841},
{"learn":[0.1825843006],"iteration":385,"passed_time":6.029071283,"remaining_time":9.590284372},
{"learn":[0.1825354589],"iteration":386,"passed_time":6.041542607,"remaining_time":9.569678599},
{"learn":[0.182494282],"iteration":387,"passed_time":6.056899314,"remaining_time":9.553665929},
{"learn":[0.1824229921],"iteration":388,"passed_time":6.071782763,"remaining_time":9.536913286},
{"learn":[0.1823798159],"iteration":389,"passed_time":6.082315025,"remaining_time":9.513364526},
{"learn":[0.1822876136],"iteration":390,"passed_time":6.100043597,"remaining_time":9.501090923},
{"learn":[0.1821126114],"iteration":391,"passed_time":6.113184304,"remaining_time":9.481673615},
{"learn":[0.1820696752],"iteration":392,"passed_time":6.12589501,"remaining_time":9.4616241},
{"learn":[0.181973905],"iteration":393,"passed_time":6.135041686,"remaining_time":9.436130106},
{"learn":[0.1819197225],"iteration":394,"passed_time":6.159509403,"remaining_time":9.434185287},
{"learn":[0.1818551379],"iteration":395,"passed_time":6.168206033,"remaining_time":9.408071829},
{"learn":[0.1818034495],"iteration":396,"passed_time":6.180995518,"remaining_time":9.388262714},
{"learn":[0.1817561839],"iteration":397,"passed_time":6.205778855,"remaining_time":9.386630329},
{"learn":[0.1816887071],"iteration":398,"passed_time":6.216217457,"remaining_time":9.363274916},
{"learn":[0.181597845],"iteration":399,"passed_time":6.234030844,"remaining_time":9.351046266},
{"learn":[0.1815346426],"iteration":400,"passed_time":6.247551935,"remaining_time":9.332378078},
{"learn":[0.1814814512],"iteration":401,"passed_time":6.259189537,"remaining_time":9.31093369},
{"learn":[0.1814291401],"iteration":402,"passed_time":6.269969166,"remaining_time":9.288266978},
{"learn":[0.1813525383],"iteration":403,"passed_time":6.292624669,"remaining_time":9.283178968},
{"learn":[0.1813147148],"iteration":404,"passed_time":6.30918073,"remaining_time":9.269043295},
{"learn":[0.1812356003],"iteration":405,"passed_time":6.324600618,"remaining_time":9.253233417},
{"learn":[0.1811646011],"iteration":406,"passed_time":6.340349295,"remaining_time":9.237904501},
{"learn":[0.1810731285],"iteration":407,"passed_time":6.350892958,"remaining_time":9.215021155},
{"learn":[0.1810057291],"iteration":408,"passed_time":6.368099877,"remaining_time":9.201826473},
{"learn":[0.1809608916],"iteration":409,"passed_time":6.379818296,"remaining_time":9.180714134},
{"learn":[0.1808760954],"iteration":410,"passed_time":6.394412975,"remaining_time":9.163769445},
{"learn":[0.1808289429],"iteration":411,"passed_time":6.409145461,"remaining_time":9.147032843},
{"learn":[0.1807532058],"iteration":412,"passed_time":6.426509438,"remaining_time":9.134046102},
{"learn":[0.1805837929],"iteration":413,"passed_time":6.442149425,"remaining_time":9.118597979},
{"learn":[0.1805402595],"iteration":414,"passed_time":6.453540146,"remaining_time":9.097159001},
{"learn":[0.1804333834],"iteration":415,"passed_time":6.465454933,"remaining_time":9.07650404},
{"learn":[0.1804043329],"iteration":416,"passed_time":6.479680761,"remaining_time":9.059122024},
{"learn":[0.1802970702],"iteration":417,"passed_time":6.492989524,"remaining_time":9.040478237},
{"learn":[0.1802188627],"iteration":418,"passed_time":6.507412442,"remaining_time":9.023404842},
{"learn":[0.1801625378],"iteration":419,"passed_time":6.527065446,"remaining_time":9.013566568},
{"learn":[0.1801101538],"iteration":420,"passed_time":6.541949618,"remaining_time":8.997123109},
{"learn":[0.1799582828],"iteration":421,"passed_time":6.555998204,"remaining_time":8.979542563},
{"learn":[0.1799091619],"iteration":422,"passed_time":6.572702938,"remaining_time":8.96560188},
{"learn":[0.1798566363],"iteration":423,"passed_time":6.586622725,"remaining_time":8.947864834},
{"learn":[0.1798020265],"iteration":424,"passed_time":6.598912648,"remaining_time":8.927940641},
{"learn":[0.1797637138],"iteration":425,"passed_time":6.607352823,"remaining_time":8.902865071},
{"learn":[0.1797196261],"iteration":426,"passed_time":6.625579874,"remaining_time":8.891000627},
{"learn":[0.1796794083],"iteration":427,"passed_time":6.637460788,"remaining_time":8.870625166},
{"learn":[0.1794930753],"iteration":428,"passed_time":6.652699243,"remaining_time":8.8547582},
{"learn":[0.1793991567],"iteration":429,"passed_time":6.66797728,"remaining_time":8.838946628},
{"learn":[0.1792508331],"iteration":430,"passed_time":6.686278669,"remaining_time":8.827128916},
{"learn":[0.1792160774],"iteration":431,"passed_time":6.700880886,"remaining_time":8.810417461},
{"learn":[0.1791818363],"iteration":432,"passed_time":6.714482865,"remaining_time":8.792405969},
{"learn":[0.1790851299],"iteration":433,"passed_time":6.734213907,"remaining_time":8.782407998},
{"learn":[0.17900269],"iteration":434,"passed_time":6.746608151,"remaining_time":8.762835875},
{"learn":[0.1789215128],"iteration":435,"passed_time":6.760460434,"remaining_time":8.745182763},
{"learn":[0.1788748718],"iteration":436,"passed_time":6.770558823,"remaining_time":8.722710795},
{"learn":[0.1788389942],"iteration":437,"passed_time":6.785397069,"remaining_time":8.706377061},
{"learn":[0.178679993],"iteration":438,"passed_time":6.803476415,"remaining_time":8.694191957},
{"learn":[0.1786140174],"iteration":439,"passed_time":6.818051336,"remaining_time":8.677519882},
{"learn":[0.1785422843],"iteration":440,"passed_time":6.830472226,"remaining_time":8.658126926},
{"learn":[0.1785022468],"iteration":441,"passed_time":6.847714991,"remaining_time":8.644852862},
{"learn":[0.1784461681],"iteration":442,"passed_time":6.863191849,"remaining_time":8.629340541},
{"learn":[0.1783678457],"iteration":443,"passed_time":6.879663295,"remaining_time":8.615073855},
{"learn":[0.1783215756],"iteration":444,"passed_time":6.894168761,"remaining_time":8.598345309},
{"learn":[0.1781519238],"iteration":445,"passed_time":6.908588019,"remaining_time":8.581519647},
{"learn":[0.1781132223],"iteration":446,"passed_time":6.930274862,"remaining_time":8.573695746},
{"learn":[0.1780184905],"iteration":447,"passed_time":6.943427046,"remaining_time":8.555294039},
{"learn":[0.17797611],"iteration":448,"passed_time":6.959624246,"remaining_time":8.540652471},
{"learn":[0.1779170303],"iteration":449,"passed_time":6.973018565,"remaining_time":8.522578246},
{"learn":[0.1778798215],"iteration":450,"passed_time":6.984701402,"remaining_time":8.502441396},
{"learn":[0.1778493397],"iteration":451,"passed_time":6.994466791,"remaining_time":8.48001726},
{"learn":[0.17769157],"iteration":452,"passed_time":7.010071756,"remaining_time":8.464700333},
{"learn":[0.1776316091],"iteration":453,"passed_time":7.023718889,"remaining_time":8.447027563},
{"learn":[0.1775463148],"iteration":454,"passed_time":7.044940093,"remaining_time":8.438444727},
{"learn":[0.1775202961],"iteration":455,"passed_time":7.057578886,"remaining_time":8.419567794},
{"learn":[0.1774970069],"iteration":456,"passed_time":7.069498295,"remaining_time":8.399863401},
{"learn":[0.1774234566],"iteration":457,"passed_time":7.085299692,"remaining_time":8.384786972},
{"learn":[0.1773429044],"iteration":458,"passed_time":7.102416505,"remaining_time":8.371257798},
{"learn":[0.1773155678],"iteration":459,"passed_time":7.111104751,"remaining_time":8.347818621},
{"learn":[0.1772734435],"iteration":460,"passed_time":7.137181762,"remaining_time":8.344774338},
{"learn":[0.1772299199],"iteration":461,"passed_time":7.146802907,"remaining_time":8.322467455},
{"learn":[0.1771558455],"iteration":462,"passed_time":7.160745639,"remaining_time":8.305227663},
{"learn":[0.177016048],"iteration":463,"passed_time":7.183552276,"remaining_time":8.298241422},
{"learn":[0.1769225608],"iteration":464,"passed_time":7.206557895,"remaining_time":8.291416073},
{"learn":[0.1768965415],"iteration":465,"passed_time":7.220407757,"remaining_time":8.27402949},
{"learn":[0.1768456259],"iteration":466,"passed_time":7.236797813,"remaining_time":8.259557247},
{"learn":[0.1768210881],"iteration":467,"passed_time":7.254298503,"remaining_time":8.246339324},
{"learn":[0.1767452512],"iteration":468,"passed_time":7.269831696,"remaining_time":8.230875545},
{"learn":[0.1767052031],"iteration":469,"passed_time":7.281829754,"remaining_time":8.211425042},
{"learn":[0.1766485755],"iteration":470,"passed_time":7.298427686,"remaining_time":8.197172497},
{"learn":[0.1766163043],"iteration":471,"passed_time":7.307471583,"remaining_time":8.174459737},
{"learn":[0.1765432366],"iteration":472,"passed_time":7.329005021,"remaining_time":8.165720182},
{"learn":[0.1764222497],"iteration":473,"passed_time":7.340127905,"remaining_time":8.145374005},
{"learn":[0.1763762249],"iteration":474,"passed_time":7.350930194,"remaining_time":8.124712319},
{"learn":[0.1763121087],"iteration":475,"passed_time":7.362948694,"remaining_time":8.105430916},
{"learn":[0.1762371462],"iteration":476,"passed_time":7.379738497,"remaining_time":8.091411392},
{"learn":[0.1761832455],"iteration":477,"passed_time":7.388307104,"remaining_time":8.068402318},
{"learn":[0.1761403745],"iteration":478,"passed_time":7.404130627,"remaining_time":8.053344585},
{"learn":[0.176090005],"iteration":479,"passed_time":7.418330964,"remaining_time":8.036525212},
{"learn":[0.1760105003],"iteration":480,"passed_time":7.430293396,"remaining_time":8.017302021},
{"learn":[0.1759469076],"iteration":481,"passed_time":7.438699205,"remaining_time":7.994286698},
{"learn":[0.1758355738],"iteration":482,"passed_time":7.466428027,"remaining_time":7.992015093},
{"learn":[0.1757627398],"iteration":483,"passed_time":7.485198111,"remaining_time":7.980087243},
{"learn":[0.175672667],"iteration":484,"passed_time":7.502842548,"remaining_time":7.966935902},
{"learn":[0.1755956853],"iteration":485,"passed_time":7.515829159,"remaining_time":7.948839892},
{"learn":[0.1755201374],"iteration":486,"passed_time":7.536838793,"remaining_time":7.939216223},
{"learn":[0.1754607366],"iteration":487,"passed_time":7.551312026,"remaining_time":7.922688028},
{"learn":[0.1754205919],"iteration":488,"passed_time":7.569476403,"remaining_time":7.910025444},
{"learn":[0.1753523388],"iteration":489,"passed_time":7.584558847,"remaining_time":7.894132678},
{"learn":[0.1752837769],"iteration":490,"passed_time":7.603122454,"remaining_time":7.881851994},
{"learn":[0.1751629036],"iteration":491,"passed_time":7.618423602,"remaining_time":7.866177215},
{"learn":[0.1751122407],"iteration":492,"passed_time":7.62895462,"remaining_time":7.845598361},
{"learn":[0.1750630079],"iteration":493,"passed_time":7.647794114,"remaining_time":7.83357049},
{"learn":[0.1750311807],"iteration":494,"passed_time":7.663974028,"remaining_time":7.818801786},
{"learn":[0.1750032206],"iteration":495,"passed_time":7.680517863,"remaining_time":7.804397183},
{"learn":[0.1749470806],"iteration":496,"passed_time":7.697898907,"remaining_time":7.790831288},
{"learn":[0.1748124697],"iteration":497,"passed_time":7.711601608,"remaining_time":7.773542183},
{"learn":[0.1747891778],"iteration":498,"passed_time":7.731796256,"remaining_time":7.762785419},
{"learn":[0.174724817],"iteration":499,"passed_time":7.744724972,"remaining_time":7.744724972},
{"learn":[0.1746448094],"iteration":500,"passed_time":7.760995916,"remaining_time":7.730013897},
{"learn":[0.1746060436],"iteration":501,"passed_time":7.782926591,"remaining_time":7.72091124},
{"learn":[0.1745422882],"iteration":502,"passed_time":7.794528821,"remaining_time":7.701552334},
{"learn":[0.1744859152],"iteration":503,"passed_time":7.812452194,"remaining_time":7.688445017},
{"learn":[0.1744380119],"iteration":504,"passed_time":7.827063092,"remaining_time":7.672071744},
{"learn":[0.1743781346],"iteration":505,"passed_time":7.845059576,"remaining_time":7.659010732},
{"learn":[0.174330965],"iteration":506,"passed_time":7.867179613,"remaining_time":7.649939939},
{"learn":[0.1742622613],"iteration":507,"passed_time":7.877653133,"remaining_time":7.629538074},
{"learn":[0.1741786123],"iteration":508,"passed_time":7.905869924,"remaining_time":7.626291027},
{"learn":[0.1741565534],"iteration":509,"passed_time":7.916740692,"remaining_time":7.606280273},
{"learn":[0.1741181692],"iteration":510,"passed_time":7.925671665,"remaining_time":7.58444901},
{"learn":[0.1740503977],"iteration":511,"passed_time":7.943474732,"remaining_time":7.571124354},
{"learn":[0.1739933539],"iteration":512,"passed_time":7.96170255,"remaining_time":7.558185461},
{"learn":[0.1739671178],"iteration":513,"passed_time":7.978299844,"remaining_time":7.543684289},
{"learn":[0.1739148329],"iteration":514,"passed_time":7.993112515,"remaining_time":7.52749431},
{"learn":[0.1738650929],"iteration":515,"passed_time":8.006776247,"remaining_time":7.510231984},
{"learn":[0.1737985722],"iteration":516,"passed_time":8.028590665,"remaining_time":7.500598242},
{"learn":[0.1737521781],"iteration":517,"passed_time":8.039058244,"remaining_time":7.480359216},
{"learn":[0.1736563445],"iteration":518,"passed_time":8.053746393,"remaining_time":7.464069393},
{"learn":[0.1736210648],"iteration":519,"passed_time":8.073397539,"remaining_time":7.452366959},
{"learn":[0.1735147835],"iteration":520,"passed_time":8.089973015,"remaining_time":7.437806285},
{"learn":[0.1734924075],"iteration":521,"passed_time":8.107572363,"remaining_time":7.424175459},
{"learn":[0.1734695579],"iteration":522,"passed_time":8.121968261,"remaining_time":7.407607764},
{"learn":[0.1733979333],"iteration":523,"passed_time":8.135424015,"remaining_time":7.390194334},
{"learn":[0.17334536],"iteration":524,"passed_time":8.15414397,"remaining_time":7.37755883},
{"learn":[0.173291318],"iteration":525,"passed_time":8.173589965,"remaining_time":7.365554455},
{"learn":[0.1732313316],"iteration":526,"passed_time":8.184388869,"remaining_time":7.345760788},
{"learn":[0.1731443203],"iteration":527,"passed_time":8.198321696,"remaining_time":7.328802728},
{"learn":[0.1731033206],"iteration":528,"passed_time":8.211033917,"remaining_time":7.310769329},
{"learn":[0.1729851984],"iteration":529,"passed_time":8.222113294,"remaining_time":7.291308016},
{"learn":[0.1729320057],"iteration":530,"passed_time":8.233426154,"remaining_time":7.272084494},
{"learn":[0.1728679134],"iteration":531,"passed_time":8.254007096,"remaining_time":7.261043836},
{"learn":[0.1728228941],"iteration":532,"passed_time":8.267991521,"remaining_time":7.244187693},
{"learn":[0.1727254304],"iteration":533,"passed_time":8.280810509,"remaining_time":7.226325276},
{"learn":[0.1726657048],"iteration":534,"passed_time":8.303548192,"remaining_time":7.217102634},
{"learn":[0.1726217505],"iteration":535,"passed_time":8.317996938,"remaining_time":7.200654066},
{"learn":[0.1725344109],"iteration":536,"passed_time":8.33560506,"remaining_time":7.186936951},
{"learn":[0.1724372874],"iteration":537,"passed_time":8.3521613,"remaining_time":7.172302083},
{"learn":[0.1723728157],"iteration":538,"passed_time":8.365494513,"remaining_time":7.15490347},
{"learn":[0.1723317795],"iteration":539,"passed_time":8.381010464,"remaining_time":7.139379284},
{"learn":[0.1722895941],"iteration":540,"passed_time":8.400278348,"remaining_time":7.127038376},
{"learn":[0.1722489474],"iteration":541,"passed_time":8.418456982,"remaining_time":7.113751472},
{"learn":[0.1722118852],"iteration":542,"passed_time":8.429961801,"remaining_time":7.094829729},
{"learn":[0.1721634232],"iteration":543,"passed_time":8.447516686,"remaining_time":7.081006634},
{"learn":[0.1721178302],"iteration":544,"passed_time":8.460654878,"remaining_time":7.063482513},
{"learn":[0.1720662638],"iteration":545,"passed_time":8.469268766,"remaining_time":7.04221249},
{"learn":[0.1720215126],"iteration":546,"passed_time":8.479520285,"remaining_time":7.022344952},
{"learn":[0.1719978503],"iteration":547,"passed_time":8.499342945,"remaining_time":7.010406955},
{"learn":[0.171940623],"iteration":548,"passed_time":8.5149757,"remaining_time":6.994998252},
{"learn":[0.1718965591],"iteration":549,"passed_time":8.525625202,"remaining_time":6.975511529},
{"learn":[0.1718358083],"iteration":550,"passed_time":8.534414781,"remaining_time":6.954541264},
{"learn":[0.1717930373],"iteration":551,"passed_time":8.548509075,"remaining_time":6.937920409},
{"learn":[0.1717480053],"iteration":552,"passed_time":8.563480236,"remaining_time":6.922017479},
{"learn":[0.1716882021],"iteration":553,"passed_time":8.579842877,"remaining_time":6.907238129},
{"learn":[0.1715527937],"iteration":554,"passed_time":8.597891795,"remaining_time":6.893805133},
{"learn":[0.171488981],"iteration":555,"passed_time":8.608025477,"remaining_time":6.874034734},
{"learn":[0.1714165572],"iteration":556,"passed_time":8.627065381,"remaining_time":6.86138234},
{"learn":[0.1713585875],"iteration":557,"passed_time":8.641352177,"remaining_time":6.844942047},
{"learn":[0.1712981784],"iteration":558,"passed_time":8.656985225,"remaining_time":6.829571528},
{"learn":[0.171246714],"iteration":559,"passed_time":8.675065723,"remaining_time":6.816123068},
{"learn":[0.1711697175],"iteration":560,"passed_time":8.695166088,"remaining_time":6.804238704},
{"learn":[0.1710818509],"iteration":561,"passed_time":8.708988399,"remaining_time":6.78743224},
{"learn":[0.1710295058],"iteration":562,"passed_time":8.726041286,"remaining_time":6.773143946},
{"learn":[0.170989576],"iteration":563,"passed_time":8.741750741,"remaining_time":6.75780731},
{"learn":[0.1709663508],"iteration":564,"passed_time":8.753662357,"remaining_time":6.739545355},
{"learn":[0.170906685],"iteration":565,"passed_time":8.766319889,"remaining_time":6.721877794},
{"learn":[0.1708448985],"iteration":566,"passed_time":8.784766316,"remaining_time":6.708648703},
{"learn":[0.170772866],"iteration":567,"passed_time":8.793520638,"remaining_time":6.688029781},
{"learn":[0.1707143476],"iteration":568,"passed_time":8.810435788,"remaining_time":6.673634138},
{"learn":[0.1706686822],"iteration":569,"passed_time":8.824742628,"remaining_time":6.657261983},
{"learn":[0.1706171351],"iteration":570,"passed_time":8.836452035,"remaining_time":6.638945574},
{"learn":[0.1705960518],"iteration":571,"passed_time":8.852641866,"remaining_time":6.624004753},
{"learn":[0.1705549554],"iteration":572,"passed_time":8.869177259,"remaining_time":6.609317085},
{"learn":[0.1705121422],"iteration":573,"passed_time":8.881393022,"remaining_time":6.591417121},
{"learn":[0.1704845132],"iteration":574,"passed_time":8.89209765,"remaining_time":6.572420002},
{"learn":[0.1703546558],"iteration":575,"passed_time":8.908520447,"remaining_time":6.557660884},
{"learn":[0.1703079477],"iteration":576,"passed_time":8.918424416,"remaining_time":6.538117033},
{"learn":[0.1702694194],"iteration":577,"passed_time":8.935186273,"remaining_time":6.523613507},
{"learn":[0.1702076453],"iteration":578,"passed_time":8.949657259,"remaining_time":6.507436453},
{"learn":[0.1701635045],"iteration":579,"passed_time":8.965030246,"remaining_time":6.491918454},
{"learn":[0.1701148162],"iteration":580,"passed_time":8.977690862,"remaining_time":6.474444873},
{"learn":[0.170071805],"iteration":581,"passed_time":8.987631207,"remaining_time":6.455034097},
{"learn":[0.1700300905],"iteration":582,"passed_time":8.99815875,"remaining_time":6.436075813},
{"learn":[0.1699725643],"iteration":583,"passed_time":9.013209658,"remaining_time":6.420368524},
{"learn":[0.1699289846],"iteration":584,"passed_time":9.031612347,"remaining_time":6.407041238},
{"learn":[0.1698753419],"iteration":585,"passed_time":9.04366862,"remaining_time":6.389212984},
{"learn":[0.1698592335],"iteration":586,"passed_time":9.053768354,"remaining_time":6.37002782},
{"learn":[0.1698394153],"iteration":587,"passed_time":9.071088205,"remaining_time":6.355932552},
{"learn":[0.169799815],"iteration":588,"passed_time":9.085042067,"remaining_time":6.339477571},
{"learn":[0.1697197564],"iteration":589,"passed_time":9.105042196,"remaining_time":6.327232712},
{"learn":[0.1696419633],"iteration":590,"passed_time":9.118471885,"remaining_time":6.310414553},
{"learn":[0.1695826912],"iteration":591,"passed_time":9.147205134,"remaining_time":6.30415489},
{"learn":[0.1695438842],"iteration":592,"passed_time":9.160676814,"remaining_time":6.287344795},
{"learn":[0.169508268],"iteration":593,"passed_time":9.170667211,"remaining_time":6.268166477},
{"learn":[0.1694713106],"iteration":594,"passed_time":9.192764183,"remaining_time":6.257259654},
{"learn":[0.1694214813],"iteration":595,"passed_time":9.201669454,"remaining_time":6.237373254},
{"learn":[0.1693688726],"iteration":596,"passed_time":9.220471246,"remaining_time":6.224204208},
{"learn":[0.1693039432],"iteration":597,"passed_time":9.235492566,"remaining_time":6.208474936},
{"learn":[0.1692502857],"iteration":598,"passed_time":9.245786632,"remaining_time":6.189583371},
{"learn":[0.1691956171],"iteration":599,"passed_time":9.262435061,"remaining_time":6.174956707},
{"learn":[0.1691693341],"iteration":600,"passed_time":9.279293475,"remaining_time":6.160462723},
{"learn":[0.1691163215],"iteration":601,"passed_time":9.29045903,"remaining_time":6.142197166},
{"learn":[0.1690837606],"iteration":602,"passed_time":9.299650784,"remaining_time":6.122655657},
{"learn":[0.1690516277],"iteration":603,"passed_time":9.31528168,"remaining_time":6.107370108},
{"learn":[0.1689935008],"iteration":604,"passed_time":9.328607926,"remaining_time":6.090578728},
{"learn":[0.1689602695],"iteration":605,"passed_time":9.344309807,"remaining_time":6.07534334},
{"learn":[0.1689223297],"iteration":606,"passed_time":9.360506393,"remaining_time":6.060426709},
{"learn":[0.1688494717],"iteration":607,"passed_time":9.372576799,"remaining_time":6.042845568},
{"learn":[0.1688169552],"iteration":608,"passed_time":9.39065452,"remaining_time":6.029139437},
{"learn":[0.1687494588],"iteration":609,"passed_time":9.403968695,"remaining_time":6.012373428},
{"learn":[0.1686787993],"iteration":610,"passed_time":9.415958112,"remaining_time":5.994775296},
{"learn":[0.1686540155],"iteration":611,"passed_time":9.439524936,"remaining_time":5.984535417},
{"learn":[0.1686204753],"iteration":612,"passed_time":9.45387032,"remaining_time":5.968430365},
{"learn":[0.1685625176],"iteration":613,"passed_time":9.471357563,"remaining_time":5.95430622},
{"learn":[0.1685368725],"iteration":614,"passed_time":9.488180621,"remaining_time":5.939755348},
{"learn":[0.1685054668],"iteration":615,"passed_time":9.505542135,"remaining_time":5.92553276},
{"learn":[0.1684472727],"iteration":616,"passed_time":9.522835646,"remaining_time":5.911257783},
{"learn":[0.1683883034],"iteration":617,"passed_time":9.534330258,"remaining_time":5.893388606},
{"learn":[0.1683530723],"iteration":618,"passed_time":9.543598799,"remaining_time":5.874169858},
{"learn":[0.1682759301],"iteration":619,"passed_time":9.56645032,"remaining_time":5.863308261},
{"learn":[0.1682273678],"iteration":620,"passed_time":9.576346851,"remaining_time":5.84450154},
{"learn":[0.1681999348],"iteration":621,"passed_time":9.589161045,"remaining_time":5.827496584},
{"learn":[0.1681600892],"iteration":622,"passed_time":9.605325328,"remaining_time":5.812532342},
{"learn":[0.1681405635],"iteration":623,"passed_time":9.618638501,"remaining_time":5.795846276},
{"learn":[0.168106555],"iteration":624,"passed_time":9.641185607,"remaining_time":5.784711364},
{"learn":[0.168068907],"iteration":625,"passed_time":9.652244554,"remaining_time":5.766676459},
{"learn":[0.1680385879],"iteration":626,"passed_time":9.67039202,"remaining_time":5.752880739},
{"learn":[0.1679785359],"iteration":627,"passed_time":9.684036859,"remaining_time":5.736403999},
{"learn":[0.1679060742],"iteration":628,"passed_time":9.701019509,"remaining_time":5.721904988},
{"learn":[0.1678878238],"iteration":629,"passed_time":9.716684969,"remaining_time":5.706624506},
{"learn":[0.1678512777],"iteration":630,"passed_time":9.728687541,"remaining_time":5.689200796},
{"learn":[0.1678184621],"iteration":631,"passed_time":9.750951275,"remaining_time":5.677769097},
{"learn":[0.1677789616],"iteration":632,"passed_time":9.764915727,"remaining_time":5.661491425},
{"learn":[0.1677349771],"iteration":633,"passed_time":9.781779863,"remaining_time":5.646895},
{"learn":[0.1676721108],"iteration":634,"passed_time":9.796821581,"remaining_time":5.631243901},
{"learn":[0.1676392841],"iteration":635,"passed_time":9.812539476,"remaining_time":5.615981713},
{"learn":[0.1676110237],"iteration":636,"passed_time":9.825156875,"remaining_time":5.598951249},
{"learn":[0.1675482472],"iteration":637,"passed_time":9.843465012,"remaining_time":5.585163533},
{"learn":[0.1674593633],"iteration":638,"passed_time":9.852392618,"remaining_time":5.566062184},
{"learn":[0.1674147684],"iteration":639,"passed_time":9.871298929,"remaining_time":5.552605647},
{"learn":[0.1673804263],"iteration":640,"passed_time":9.881981614,"remaining_time":5.534526364},
{"learn":[0.1673494423],"iteration":641,"passed_time":9.898758042,"remaining_time":5.519868191},
{"learn":[0.1672752937],"iteration":642,"passed_time":9.91485268,"remaining_time":5.504824894},
{"learn":[0.1672291005],"iteration":643,"passed_time":9.927635038,"remaining_time":5.487947319},
{"learn":[0.1671878508],"iteration":644,"passed_time":9.946506895,"remaining_time":5.474434027},
{"learn":[0.1671255403],"iteration":645,"passed_time":9.960975401,"remaining_time":5.458491164},
{"learn":[0.1671012808],"iteration":646,"passed_time":9.976787324,"remaining_time":5.44328582},
{"learn":[0.1670646273],"iteration":647,"passed_time":9.991959316,"remaining_time":5.427730987},
{"learn":[0.1670258287],"iteration":648,"passed_time":10.00632793,"remaining_time":5.41174284},
{"learn":[0.1669918071],"iteration":649,"passed_time":10.01525663,"remaining_time":5.392830492},
{"learn":[0.166925416],"iteration":650,"passed_time":10.04044908,"remaining_time":5.382667786},
{"learn":[0.1668866035],"iteration":651,"passed_time":10.05906089,"remaining_time":5.368946611},
{"learn":[0.1668643766],"iteration":652,"passed_time":10.0774745,"remaining_time":5.355105135},
{"learn":[0.1668181821],"iteration":653,"passed_time":10.09039179,"remaining_time":5.338341836},
{"learn":[0.1667637089],"iteration":654,"passed_time":10.10706527,"remaining_time":5.323568731},
{"learn":[0.1667050311],"iteration":655,"passed_time":10.12333924,"remaining_time":5.308580334},
{"learn":[0.1666718335],"iteration":656,"passed_time":10.13584541,"remaining_time":5.291620965},
{"learn":[0.1666544071],"iteration":657,"passed_time":10.15557903,"remaining_time":5.278431653},
{"learn":[0.1666027636],"iteration":658,"passed_time":10.17262301,"remaining_time":5.263830721},
{"learn":[0.1665789056],"iteration":659,"passed_time":10.18854772,"remaining_time":5.248645795},
{"learn":[0.16650333],"iteration":660,"passed_time":10.1992284,"remaining_time":5.230769177},
{"learn":[0.1664551744],"iteration":661,"passed_time":10.21136212,"remaining_time":5.21365619},
{"learn":[0.1663959038],"iteration":662,"passed_time":10.22177464,"remaining_time":5.195683338},
{"learn":[0.1663601682],"iteration":663,"passed_time":10.24069044,"remaining_time":5.182036129},
{"learn":[0.1662928113],"iteration":664,"passed_time":10.25639803,"remaining_time":5.166756903},
{"learn":[0.1662528631],"iteration":665,"passed_time":10.26945586,"remaining_time":5.150147532},
{"learn":[0.1662254947],"iteration":666,"passed_time":10.27921034,"remaining_time":5.131899617},
{"learn":[0.1662116679],"iteration":667,"passed_time":10.3020915,"remaining_time":5.120201162},
{"learn":[0.1661435812],"iteration":668,"passed_time":10.31362754,"remaining_time":5.102856079},
{"learn":[0.1661019092],"iteration":669,"passed_time":10.32326413,"remaining_time":5.084592778},
{"learn":[0.1660225653],"iteration":670,"passed_time":10.35083682,"remaining_time":5.0751495},
{"learn":[0.1659723151],"iteration":671,"passed_time":10.36788338,"remaining_time":5.060514506},
{"learn":[0.1659210003],"iteration":672,"passed_time":10.38291745,"remaining_time":5.044894511},
{"learn":[0.1658400178],"iteration":673,"passed_time":10.395803,"remaining_time":5.028237062},
{"learn":[0.1657978668],"iteration":674,"passed_time":10.40512206,"remaining_time":5.009873585},
{"learn":[0.1657473295],"iteration":675,"passed_time":10.42380029,"remaining_time":4.996022622},
{"learn":[0.1655609248],"iteration":676,"passed_time":10.43585532,"remaining_time":4.97899744},
{"learn":[0.1655146809],"iteration":677,"passed_time":10.45285146,"remaining_time":4.964333587},
{"learn":[0.165462566],"iteration":678,"passed_time":10.46816673,"remaining_time":4.948868221},
{"learn":[0.1654086549],"iteration":679,"passed_time":10.48640228,"remaining_time":4.934777541},
{"learn":[0.1653850186],"iteration":680,"passed_time":10.50312218,"remaining_time":4.919964724},
{"learn":[0.1653004505],"iteration":681,"passed_time":10.52019365,"remaining_time":4.905310234},
{"learn":[0.165247767],"iteration":682,"passed_time":10.53799467,"remaining_time":4.890987276},
{"learn":[0.1652151763],"iteration":683,"passed_time":10.54936263,"remaining_time":4.87368215},
{"learn":[0.1651465402],"iteration":684,"passed_time":10.58065731,"remaining_time":4.865557741},
{"learn":[0.1650960643],"iteration":685,"passed_time":10.59227774,"remaining_time":4.848360364},
{"learn":[0.165068756],"iteration":686,"passed_time":10.61579999,"remaining_time":4.836601744},
{"learn":[0.1649892987],"iteration":687,"passed_time":10.63148866,"remaining_time":4.821256483},
{"learn":[0.1649560028],"iteration":688,"passed_time":10.64684976,"remaining_time":4.805762374},
{"learn":[0.1649223867],"iteration":689,"passed_time":10.66573745,"remaining_time":4.791853057},
{"learn":[0.1648889835],"iteration":690,"passed_time":10.69989985,"remaining_time":4.784759845},
{"learn":[0.164858168],"iteration":691,"passed_time":10.72221726,"remaining_time":4.772316354},
{"learn":[0.1647649858],"iteration":692,"passed_time":10.7538963,"remaining_time":4.763991581},
{"learn":[0.164713656],"iteration":693,"passed_time":10.77692565,"remaining_time":4.751785659},
{"learn":[0.1646535957],"iteration":694,"passed_time":10.80103826,"remaining_time":4.740023984},
{"learn":[0.1646335223],"iteration":695,"passed_time":10.82209552,"remaining_time":4.726892295},
{"learn":[0.1645774668],"iteration":696,"passed_time":10.83704729,"remaining_time":4.711083687},
{"learn":[0.1645548356],"iteration":697,"passed_time":10.85673072,"remaining_time":4.697324751},
{"learn":[0.1644941199],"iteration":698,"passed_time":10.87604444,"remaining_time":4.683389667},
{"learn":[0.1644640289],"iteration":699,"passed_time":10.90683524,"remaining_time":4.674357962},
{"learn":[0.1644310386],"iteration":700,"passed_time":10.92100006,"remaining_time":4.658172637},
{"learn":[0.1644011587],"iteration":701,"passed_time":10.94675953,"remaining_time":4.646915015},
{"learn":[0.1643815797],"iteration":702,"passed_time":10.95697342,"remaining_time":4.629048516},
{"learn":[0.1643309589],"iteration":703,"passed_time":10.97239165,"remaining_time":4.613391944},
{"learn":[0.1642722968],"iteration":704,"passed_time":10.99346671,"remaining_time":4.600103092},
{"learn":[0.1642580333],"iteration":705,"passed_time":11.01216571,"remaining_time":4.585802719},
{"learn":[0.1642052615],"iteration":706,"passed_time":11.03023335,"remaining_time":4.571228246},
{"learn":[0.1641772505],"iteration":707,"passed_time":11.05303626,"remaining_time":4.558596875},
{"learn":[0.1640936013],"iteration":708,"passed_time":11.07098742,"remaining_time":4.543945471},
{"learn":[0.1640564484],"iteration":709,"passed_time":11.10247374,"remaining_time":4.534813217},
{"learn":[0.1640114383],"iteration":710,"passed_time":11.1132126,"remaining_time":4.517184868},
{"learn":[0.1639766904],"iteration":711,"passed_time":11.12919338,"remaining_time":4.501696199},
{"learn":[0.163899451],"iteration":712,"passed_time":11.15716444,"remaining_time":4.491032532},
{"learn":[0.1638599171],"iteration":713,"passed_time":11.18116064,"remaining_time":4.478728212},
{"learn":[0.1638269898],"iteration":714,"passed_time":11.1924057,"remaining_time":4.461308568},
{"learn":[0.1637550254],"iteration":715,"passed_time":11.22240794,"remaining_time":4.451346168},
{"learn":[0.163702868],"iteration":716,"passed_time":11.25036868,"remaining_time":4.440522088},
{"learn":[0.1636681758],"iteration":717,"passed_time":11.27410856,"remaining_time":4.4279925},
{"learn":[0.1636259383],"iteration":718,"passed_time":11.33039264,"remaining_time":4.42815067},
{"learn":[0.1635830167],"iteration":719,"passed_time":11.37353846,"remaining_time":4.423042733},
{"learn":[0.1635052799],"iteration":720,"passed_time":11.47246153,"remaining_time":4.43941299},
{"learn":[0.1634741528],"iteration":721,"passed_time":11.51078748,"remaining_time":4.432131468},
{"learn":[0.1634421549],"iteration":722,"passed_time":11.58536677,"remaining_time":4.43865366},
{"learn":[0.1634036767],"iteration":723,"passed_time":11.61425959,"remaining_time":4.427535425},
{"learn":[0.1633548138],"iteration":724,"passed_time":11.66282256,"remaining_time":4.423829245},
{"learn":[0.1633154004],"iteration":725,"passed_time":11.73435137,"remaining_time":4.428667048},
{"learn":[0.1632620112],"iteration":726,"passed_time":11.78631798,"remaining_time":4.425948842},
{"learn":[0.163216374],"iteration":727,"passed_time":11.84590853,"remaining_time":4.425943847},
{"learn":[0.1631876267],"iteration":728,"passed_time":11.91876441,"remaining_time":4.43070666},
{"learn":[0.1631564896],"iteration":729,"passed_time":11.98348971,"remaining_time":4.432249617},
{"learn":[0.1630673346],"iteration":730,"passed_time":12.00486559,"remaining_time":4.417659157},
{"learn":[0.1630448443],"iteration":731,"passed_time":12.04831755,"remaining_time":4.411132654},
{"learn":[0.1630223596],"iteration":732,"passed_time":12.14401332,"remaining_time":4.423535547},
{"learn":[0.1629782159],"iteration":733,"passed_time":12.20397938,"remaining_time":4.422695524},
{"learn":[0.1629491012],"iteration":734,"passed_time":12.24495775,"remaining_time":4.414848714},
{"learn":[0.1629190467],"iteration":735,"passed_time":12.29649995,"remaining_time":4.41070107},
{"learn":[0.1628294817],"iteration":736,"passed_time":12.3584,"remaining_time":4.41012103},
{"learn":[0.1628083614],"iteration":737,"passed_time":12.40068074,"remaining_time":4.402409695},
{"learn":[0.1627919159],"iteration":738,"passed_time":12.43041887,"remaining_time":4.390174999},
{"learn":[0.1627674349],"iteration":739,"passed_time":12.45897178,"remaining_time":4.377476571},
{"learn":[0.162720712],"iteration":740,"passed_time":12.50635116,"remaining_time":4.371315724},
{"learn":[0.1626767143],"iteration":741,"passed_time":12.53696942,"remaining_time":4.359215783},
{"learn":[0.1626461166],"iteration":742,"passed_time":12.57848254,"remaining_time":4.350834471},
{"learn":[0.1625949098],"iteration":743,"passed_time":12.62148276,"remaining_time":4.342875787},
{"learn":[0.1625522513],"iteration":744,"passed_time":12.64159359,"remaining_time":4.326988409},
{"learn":[0.162500675],"iteration":745,"passed_time":12.69020428,"remaining_time":4.320793414},
{"learn":[0.1624563488],"iteration":746,"passed_time":12.7406727,"remaining_time":4.315114047},
{"learn":[0.162418089],"iteration":747,"passed_time":12.78588155,"remaining_time":4.307542983},
{"learn":[0.1623995201],"iteration":748,"passed_time":12.82182063,"remaining_time":4.296764992},
{"learn":[0.1623421547],"iteration":749,"passed_time":12.87517563,"remaining_time":4.291725211},
{"learn":[0.1623196519],"iteration":750,"passed_time":12.90642406,"remaining_time":4.279227153},
{"learn":[0.1622784132],"iteration":751,"passed_time":12.93606831,"remaining_time":4.266150187},
{"learn":[0.1622279064],"iteration":752,"passed_time":12.96761788,"remaining_time":4.253654205},
{"learn":[0.1621883817],"iteration":753,"passed_time":12.98671724,"remaining_time":4.237045676},
{"learn":[0.1621566715],"iteration":754,"passed_time":13.01760342,"remaining_time":4.224255413},
{"learn":[0.1621131008],"iteration":755,"passed_time":13.03960931,"remaining_time":4.208551152},
{"learn":[0.1620938759],"iteration":756,"passed_time":13.08074174,"remaining_time":4.198969939},
{"learn":[0.1620719445],"iteration":757,"passed_time":13.11475477,"remaining_time":4.187032524},
{"learn":[0.1620602545],"iteration":758,"passed_time":13.1357782,"remaining_time":4.170912446},
{"learn":[0.1620176269],"iteration":759,"passed_time":13.1659797,"remaining_time":4.157677799},
{"learn":[0.1619700437],"iteration":760,"passed_time":13.18603075,"remaining_time":4.141210708},
{"learn":[0.161901998],"iteration":761,"passed_time":13.21585549,"remaining_time":4.127786885},
{"learn":[0.1618610572],"iteration":762,"passed_time":13.24398718,"remaining_time":4.113794183},
{"learn":[0.1618141714],"iteration":763,"passed_time":13.26694277,"remaining_time":4.098165567},
{"learn":[0.1617463267],"iteration":764,"passed_time":13.30126913,"remaining_time":4.086010779},
{"learn":[0.1617103568],"iteration":765,"passed_time":13.34498752,"remaining_time":4.076667205},
{"learn":[0.1616453908],"iteration":766,"passed_time":13.37639819,"remaining_time":4.063495147},
{"learn":[0.1615939828],"iteration":767,"passed_time":13.40717251,"remaining_time":4.050083361},
{"learn":[0.1615762394],"iteration":768,"passed_time":13.44198714,"remaining_time":4.037840091},
{"learn":[0.1614818773],"iteration":769,"passed_time":13.46104339,"remaining_time":4.020831143},
{"learn":[0.1614325097],"iteration":770,"passed_time":13.49283383,"remaining_time":4.007599153},
{"learn":[0.1613518287],"iteration":771,"passed_time":13.52910964,"remaining_time":3.995643778},
{"learn":[0.1612644137],"iteration":772,"passed_time":13.57006826,"remaining_time":3.98500064},
{"learn":[0.1611809266],"iteration":773,"passed_time":13.59369956,"remaining_time":3.969219767},
{"learn":[0.161136077],"iteration":774,"passed_time":13.62551681,"remaining_time":3.955795202},
{"learn":[0.1610883549],"iteration":775,"passed_time":13.6468664,"remaining_time":3.93930164},
{"learn":[0.1610496617],"iteration":776,"passed_time":13.68937846,"remaining_time":3.928869237},
{"learn":[0.1609893862],"iteration":777,"passed_time":13.7224814,"remaining_time":3.9156695},
{"learn":[0.1609478331],"iteration":778,"passed_time":13.7434206,"remaining_time":3.898967846},
{"learn":[0.1609100322],"iteration":779,"passed_time":13.77544367,"remaining_time":3.885381548},
{"learn":[0.1608628586],"iteration":780,"passed_time":13.80190009,"remaining_time":3.870187093},
{"learn":[0.1608183878],"iteration":781,"passed_time":13.8263694,"remaining_time":3.854409885},
{"learn":[0.1607828439],"iteration":782,"passed_time":13.84543785,"remaining_time":3.837113681},
{"learn":[0.1607417231],"iteration":783,"passed_time":13.89846164,"remaining_time":3.829168002},
{"learn":[0.1606971493],"iteration":784,"passed_time":13.92255708,"remaining_time":3.813184422},
{"learn":[0.1606343188],"iteration":785,"passed_time":13.96672245,"remaining_time":3.802644535},
{"learn":[0.1605996633],"iteration":786,"passed_time":13.99917823,"remaining_time":3.788850015},
{"learn":[0.1605637536],"iteration":787,"passed_time":14.04010963,"remaining_time":3.777288378},
{"learn":[0.1605247375],"iteration":788,"passed_time":14.08271255,"remaining_time":3.7660993},
{"learn":[0.1604739137],"iteration":789,"passed_time":14.12928194,"remaining_time":3.755885072},
{"learn":[0.1603986526],"iteration":790,"passed_time":14.18026598,"remaining_time":3.746745373},
{"learn":[0.1603673648],"iteration":791,"passed_time":14.21340045,"remaining_time":3.732812239},
{"learn":[0.1603342109],"iteration":792,"passed_time":14.26000052,"remaining_time":3.722345659},
{"learn":[0.1602989975],"iteration":793,"passed_time":14.31375799,"remaining_time":3.713645021},
{"learn":[0.1602328744],"iteration":794,"passed_time":14.36088508,"remaining_time":3.70312131},
{"learn":[0.1601786532],"iteration":795,"passed_time":14.40774061,"remaining_time":3.692436037},
{"learn":[0.1601480117],"iteration":796,"passed_time":14.44157232,"remaining_time":3.67834276},
{"learn":[0.1601242812],"iteration":797,"passed_time":14.46122635,"remaining_time":3.660611182},
{"learn":[0.1600804649],"iteration":798,"passed_time":14.50971666,"remaining_time":3.650128972},
{"learn":[0.1599985031],"iteration":799,"passed_time":14.5385052,"remaining_time":3.6346263},
{"learn":[0.1599317742],"iteration":800,"passed_time":14.57520779,"remaining_time":3.621056616},
{"learn":[0.159815205],"iteration":801,"passed_time":14.59910025,"remaining_time":3.604266646},
{"learn":[0.1597769851],"iteration":802,"passed_time":14.62670832,"remaining_time":3.588370535},
{"learn":[0.1597455821],"iteration":803,"passed_time":14.64307337,"remaining_time":3.569704455},
{"learn":[0.1596977126],"iteration":804,"passed_time":14.65882034,"remaining_time":3.550894367},
{"learn":[0.1596653242],"iteration":805,"passed_time":14.68739066,"remaining_time":3.535178398},
{"learn":[0.1596297103],"iteration":806,"passed_time":14.70947623,"remaining_time":3.517879693},
{"learn":[0.1596043563],"iteration":807,"passed_time":14.73990545,"remaining_time":3.502551789},
{"learn":[0.1595612379],"iteration":808,"passed_time":14.77233068,"remaining_time":3.487657799},
{"learn":[0.1595334881],"iteration":809,"passed_time":14.78912354,"remaining_time":3.469053671},
{"learn":[0.159512321],"iteration":810,"passed_time":14.82104316,"remaining_time":3.453979232},
{"learn":[0.1594844125],"iteration":811,"passed_time":14.8379259,"remaining_time":3.435381858},
{"learn":[0.1594093142],"iteration":812,"passed_time":14.87913735,"remaining_time":3.422384606},
{"learn":[0.1593670925],"iteration":813,"passed_time":14.89682312,"remaining_time":3.403942385},
{"learn":[0.1593044529],"iteration":814,"passed_time":14.91272708,"remaining_time":3.385097559},
{"learn":[0.1592709233],"iteration":815,"passed_time":14.95049701,"remaining_time":3.371190502},
{"learn":[0.1592375865],"iteration":816,"passed_time":14.96803175,"remaining_time":3.352692546},
{"learn":[0.159164495],"iteration":817,"passed_time":15.00119991,"remaining_time":3.337675286},
{"learn":[0.1591319465],"iteration":818,"passed_time":15.01962725,"remaining_time":3.31935596},
{"learn":[0.1591021426],"iteration":819,"passed_time":15.03422294,"remaining_time":3.30019528},
{"learn":[0.1590640061],"iteration":820,"passed_time":15.06717439,"remaining_time":3.285047766},
{"learn":[0.1590373592],"iteration":821,"passed_time":15.08385942,"remaining_time":3.266334522},
{"learn":[0.1589889909],"iteration":822,"passed_time":15.09985132,"remaining_time":3.247477138},
{"learn":[0.1589521274],"iteration":823,"passed_time":15.1365644,"remaining_time":3.233052591},
{"learn":[0.1588714098],"iteration":824,"passed_time":15.15042873,"remaining_time":3.213727307},
{"learn":[0.1588398419],"iteration":825,"passed_time":15.17673932,"remaining_time":3.197037097},
{"learn":[0.1587821546],"iteration":826,"passed_time":15.19945638,"remaining_time":3.179571892},
{"learn":[0.1587558109],"iteration":827,"passed_time":15.22880066,"remaining_time":3.163470668},
{"learn":[0.1587147947],"iteration":828,"passed_time":15.24830775,"remaining_time":3.145308353},
{"learn":[0.1586895808],"iteration":829,"passed_time":15.26835128,"remaining_time":3.127252672},
{"learn":[0.1586583104],"iteration":830,"passed_time":15.29417879,"remaining_time":3.11036849},
{"learn":[0.1586175527],"iteration":831,"passed_time":15.31527474,"remaining_time":3.092507399},
{"learn":[0.1585818777],"iteration":832,"passed_time":15.33642214,"remaining_time":3.074648856},
{"learn":[0.1585281409],"iteration":833,"passed_time":15.36108723,"remaining_time":3.05748259},
{"learn":[0.1584911729],"iteration":834,"passed_time":15.38841522,"remaining_time":3.040824564},
{"learn":[0.1584075555],"iteration":835,"passed_time":15.41195396,"remaining_time":3.023397667},
{"learn":[0.1583909694],"iteration":836,"passed_time":15.44476417,"remaining_time":3.00776172},
{"learn":[0.1583554695],"iteration":837,"passed_time":15.46098344,"remaining_time":2.988877466},
{"learn":[0.1583157632],"iteration":838,"passed_time":15.48988911,"remaining_time":2.972434025},
{"learn":[0.158279479],"iteration":839,"passed_time":15.51115402,"remaining_time":2.954505527},
{"learn":[0.158215748],"iteration":840,"passed_time":15.53951905,"remaining_time":2.93791145},
{"learn":[0.158176205],"iteration":841,"passed_time":15.55989969,"remaining_time":2.919791153},
{"learn":[0.1581525656],"iteration":842,"passed_time":15.59220948,"remaining_time":2.903887175},
{"learn":[0.1581284565],"iteration":843,"passed_time":15.61071404,"remaining_time":2.885392642},
{"learn":[0.1581102482],"iteration":844,"passed_time":15.62473334,"remaining_time":2.866075346},
{"learn":[0.1580605247],"iteration":845,"passed_time":15.6583539,"remaining_time":2.850338653},
{"learn":[0.1580333956],"iteration":846,"passed_time":15.67404346,"remaining_time":2.831320719},
{"learn":[0.1579753417],"iteration":847,"passed_time":15.6986938,"remaining_time":2.813916813},
{"learn":[0.1579480291],"iteration":848,"passed_time":15.72338208,"remaining_time":2.796502585},
{"learn":[0.1579009414],"iteration":849,"passed_time":15.74027429,"remaining_time":2.777695462},
{"learn":[0.1578660955],"iteration":850,"passed_time":15.77406218,"remaining_time":2.761851075},
{"learn":[0.1578318814],"iteration":851,"passed_time":15.78987129,"remaining_time":2.742841491},
{"learn":[0.1577936176],"iteration":852,"passed_time":15.82033476,"remaining_time":2.726364842},
{"learn":[0.1577379806],"iteration":853,"passed_time":15.84174937,"remaining_time":2.70830844},
{"learn":[0.1576957801],"iteration":854,"passed_time":15.87380244,"remaining_time":2.692048367},
{"learn":[0.1576215742],"iteration":855,"passed_time":15.90539578,"remaining_time":2.675674056},
{"learn":[0.1575950928],"iteration":856,"passed_time":15.92251511,"remaining_time":2.656849078},
{"learn":[0.1575115276],"iteration":857,"passed_time":15.95207135,"remaining_time":2.6400864},
{"learn":[0.1574804794],"iteration":858,"passed_time":15.97121748,"remaining_time":2.621585174},
{"learn":[0.1573912836],"iteration":859,"passed_time":16.00495881,"remaining_time":2.605458411},
{"learn":[0.1573664858],"iteration":860,"passed_time":16.02012031,"remaining_time":2.5862912},
{"learn":[0.1573105948],"iteration":861,"passed_time":16.04936599,"remaining_time":2.569388059},
{"learn":[0.1572824091],"iteration":862,"passed_time":16.0726759,"remaining_time":2.551514019},
{"learn":[0.1572450754],"iteration":863,"passed_time":16.10548907,"remaining_time":2.53512328},
{"learn":[0.157201248],"iteration":864,"passed_time":16.12737576,"remaining_time":2.51698928},
{"learn":[0.1571455693],"iteration":865,"passed_time":16.1520841,"remaining_time":2.499283221},
{"learn":[0.1571019798],"iteration":866,"passed_time":16.18453773,"remaining_time":2.482749155},
{"learn":[0.1570630144],"iteration":867,"passed_time":16.20048434,"remaining_time":2.463668125},
{"learn":[0.1570209339],"iteration":868,"passed_time":16.21693484,"remaining_time":2.44467027},
{"learn":[0.1569843901],"iteration":869,"passed_time":16.24545641,"remaining_time":2.427481993},
{"learn":[0.1569563562],"iteration":870,"passed_time":16.26578688,"remaining_time":2.409054543},
{"learn":[0.1569234927],"iteration":871,"passed_time":16.29807255,"remaining_time":2.392377623},
{"learn":[0.1568950736],"iteration":872,"passed_time":16.33103041,"remaining_time":2.375762729},
{"learn":[0.1568662404],"iteration":873,"passed_time":16.34802003,"remaining_time":2.356808379},
{"learn":[0.1568277027],"iteration":874,"passed_time":16.36697193,"remaining_time":2.338138847},
{"learn":[0.1568116753],"iteration":875,"passed_time":16.38956323,"remaining_time":2.319983836},
{"learn":[0.1567890538],"iteration":876,"passed_time":16.40056106,"remaining_time":2.300192714},
{"learn":[0.1567716881],"iteration":877,"passed_time":16.43237417,"remaining_time":2.28331395},
{"learn":[0.1567499664],"iteration":878,"passed_time":16.44802265,"remaining_time":2.264176042},
{"learn":[0.1566729816],"iteration":879,"passed_time":16.47548497,"remaining_time":2.246657041},
{"learn":[0.1566603282],"iteration":880,"passed_time":16.5134893,"remaining_time":2.230539417},
{"learn":[0.1565743842],"iteration":881,"passed_time":16.52846368,"remaining_time":2.21129106},
{"learn":[0.1565420656],"iteration":882,"passed_time":16.55957939,"remaining_time":2.194191154},
{"learn":[0.1565119331],"iteration":883,"passed_time":16.5783991,"remaining_time":2.175446035},
{"learn":[0.1564761575],"iteration":884,"passed_time":16.60932995,"remaining_time":2.158274513},
{"learn":[0.1564371469],"iteration":885,"passed_time":16.62839422,"remaining_time":2.13954508},
{"learn":[0.1563974126],"iteration":886,"passed_time":16.64919464,"remaining_time":2.12103607},
{"learn":[0.1563598384],"iteration":887,"passed_time":16.67410882,"remaining_time":2.103040752},
{"learn":[0.1563198801],"iteration":888,"passed_time":16.70626354,"remaining_time":2.085933917},
{"learn":[0.156293537],"iteration":889,"passed_time":16.72545641,"remaining_time":2.067191241},
{"learn":[0.1562813908],"iteration":890,"passed_time":16.74191117,"remaining_time":2.04811259},
{"learn":[0.1562696276],"iteration":891,"passed_time":16.77176998,"remaining_time":2.030662732},
{"learn":[0.1561974042],"iteration":892,"passed_time":16.78889001,"remaining_time":2.011658713},
{"learn":[0.1561552514],"iteration":893,"passed_time":16.82594654,"remaining_time":1.995022744},
{"learn":[0.1561280856],"iteration":894,"passed_time":16.85107133,"remaining_time":1.97694133},
{"learn":[0.1560886303],"iteration":895,"passed_time":16.8693807,"remaining_time":1.958053117},
{"learn":[0.156042505],"iteration":896,"passed_time":16.89588967,"remaining_time":1.940107733},
{"learn":[0.1560305666],"iteration":897,"passed_time":16.90796425,"remaining_time":1.920503734},
{"learn":[0.1559883004],"iteration":898,"passed_time":16.93750617,"remaining_time":1.902878891},
{"learn":[0.155968416],"iteration":899,"passed_time":16.95424819,"remaining_time":1.883805355},
{"learn":[0.1559348551],"iteration":900,"passed_time":16.98730391,"remaining_time":1.866529509},
{"learn":[0.155901388],"iteration":901,"passed_time":17.01876935,"remaining_time":1.849045894},
{"learn":[0.155881447],"iteration":902,"passed_time":17.03791564,"remaining_time":1.830207992},
{"learn":[0.1558063815],"iteration":903,"passed_time":17.05731196,"remaining_time":1.811395961},
{"learn":[0.1556625935],"iteration":904,"passed_time":17.08555721,"remaining_time":1.79351153},
{"learn":[0.1556268215],"iteration":905,"passed_time":17.11461059,"remaining_time":1.775688075},
{"learn":[0.1556021496],"iteration":906,"passed_time":17.13578736,"remaining_time":1.757032221},
{"learn":[0.1555866283],"iteration":907,"passed_time":17.14986676,"remaining_time":1.737651698},
{"learn":[0.1555194114],"iteration":908,"passed_time":17.1747367,"remaining_time":1.71936308},
{"learn":[0.1554662249],"iteration":909,"passed_time":17.18659669,"remaining_time":1.699773299},
{"learn":[0.1554494328],"iteration":910,"passed_time":17.21531506,"remaining_time":1.681847464},
{"learn":[0.1553791664],"iteration":911,"passed_time":17.242387,"remaining_time":1.663739097},
{"learn":[0.1553410828],"iteration":912,"passed_time":17.26454405,"remaining_time":1.645142752},
{"learn":[0.155294431],"iteration":913,"passed_time":17.29779676,"remaining_time":1.627582627},
{"learn":[0.155255794],"iteration":914,"passed_time":17.31478642,"remaining_time":1.608477427},
{"learn":[0.1552308178],"iteration":915,"passed_time":17.34464212,"remaining_time":1.590556701},
{"learn":[0.1551755434],"iteration":916,"passed_time":17.36408366,"remaining_time":1.571667332},
{"learn":[0.1551398481],"iteration":917,"passed_time":17.38077354,"remaining_time":1.552530969},
{"learn":[0.1551064884],"iteration":918,"passed_time":17.40841045,"remaining_time":1.534364795},
{"learn":[0.1550642259],"iteration":919,"passed_time":17.42181897,"remaining_time":1.51494078},
{"learn":[0.1550056734],"iteration":920,"passed_time":17.45473141,"remaining_time":1.497202803},
{"learn":[0.1549758501],"iteration":921,"passed_time":17.47679445,"remaining_time":1.478514064},
{"learn":[0.1549257494],"iteration":922,"passed_time":17.508014,"remaining_time":1.460581883},
{"learn":[0.1548933485],"iteration":923,"passed_time":17.53023545,"remaining_time":1.441880838},
{"learn":[0.15487261],"iteration":924,"passed_time":17.55514073,"remaining_time":1.423389789},
{"learn":[0.1548379056],"iteration":925,"passed_time":17.57697668,"remaining_time":1.404639605},
{"learn":[0.1547691374],"iteration":926,"passed_time":17.59420743,"remaining_time":1.38552011},
{"learn":[0.1546635814],"iteration":927,"passed_time":17.62384207,"remaining_time":1.367367057},
{"learn":[0.1546058741],"iteration":928,"passed_time":17.64309539,"remaining_time":1.34839588},
{"learn":[0.1545676795],"iteration":929,"passed_time":17.67270328,"remaining_time":1.330203473},
{"learn":[0.1545224226],"iteration":930,"passed_time":17.69145423,"remaining_time":1.311181893},
{"learn":[0.1544976752],"iteration":931,"passed_time":17.71510101,"remaining_time":1.292518099},
{"learn":[0.1544556686],"iteration":932,"passed_time":17.73767094,"remaining_time":1.273766295},
{"learn":[0.1544184843],"iteration":933,"passed_time":17.76911084,"remaining_time":1.2556331},
{"learn":[0.1544036852],"iteration":934,"passed_time":17.79432359,"remaining_time":1.237038538},
{"learn":[0.1543428623],"iteration":935,"passed_time":17.83663845,"remaining_time":1.21959921},
{"learn":[0.1542989821],"iteration":936,"passed_time":17.85689607,"remaining_time":1.200623749},
{"learn":[0.1542802191],"iteration":937,"passed_time":17.92490771,"remaining_time":1.184802002},
{"learn":[0.1542336907],"iteration":938,"passed_time":17.9850185,"remaining_time":1.168355834},
{"learn":[0.1541928748],"iteration":939,"passed_time":18.0124499,"remaining_time":1.149730845},
{"learn":[0.1541422022],"iteration":940,"passed_time":18.08451584,"remaining_time":1.13388569},
{"learn":[0.1541112991],"iteration":941,"passed_time":18.10405814,"remaining_time":1.114687231},
{"learn":[0.1540776426],"iteration":942,"passed_time":18.11767992,"remaining_time":1.095130175},
{"learn":[0.1540340848],"iteration":943,"passed_time":18.13548976,"remaining_time":1.075834138},
{"learn":[0.1540044265],"iteration":944,"passed_time":18.16119639,"remaining_time":1.057000848},
{"learn":[0.1539549679],"iteration":945,"passed_time":18.17806798,"remaining_time":1.037648701},
{"learn":[0.1538834564],"iteration":946,"passed_time":18.21802741,"remaining_time":1.019593931},
{"learn":[0.153855031],"iteration":947,"passed_time":18.23393801,"remaining_time":1.000173815},
{"learn":[0.1538282292],"iteration":948,"passed_time":18.26554266,"remaining_time":0.9816045054},
{"learn":[0.153805598],"iteration":949,"passed_time":18.29046197,"remaining_time":0.9626558933},
{"learn":[0.1537550745],"iteration":950,"passed_time":18.31437189,"remaining_time":0.9436427154},
{"learn":[0.1537299502],"iteration":951,"passed_time":18.32893808,"remaining_time":0.9241481382},
{"learn":[0.1536991209],"iteration":952,"passed_time":18.35995961,"remaining_time":0.9054754478},
{"learn":[0.1536879727],"iteration":953,"passed_time":18.37832434,"remaining_time":0.8861665823},
{"learn":[0.1536358967],"iteration":954,"passed_time":18.41042743,"remaining_time":0.8675070517},
{"learn":[0.1535516796],"iteration":955,"passed_time":18.44551286,"remaining_time":0.8489566588},
{"learn":[0.1534956955],"iteration":956,"passed_time":18.48007169,"remaining_time":0.8303480488},
{"learn":[0.1534556497],"iteration":957,"passed_time":18.51187192,"remaining_time":0.8115851989},
{"learn":[0.1534081487],"iteration":958,"passed_time":18.53017226,"remaining_time":0.7922180005},
{"learn":[0.1533845657],"iteration":959,"passed_time":18.56308765,"remaining_time":0.7734619854},
{"learn":[0.1532869307],"iteration":960,"passed_time":18.57857509,"remaining_time":0.7539692285},
{"learn":[0.1532294302],"iteration":961,"passed_time":18.60636239,"remaining_time":0.7349706559},
{"learn":[0.1531944596],"iteration":962,"passed_time":18.64065924,"remaining_time":0.7162039374},
{"learn":[0.1531208326],"iteration":963,"passed_time":18.67169784,"remaining_time":0.6972833217},
{"learn":[0.153078353],"iteration":964,"passed_time":18.69466372,"remaining_time":0.6780447983},
{"learn":[0.1530335686],"iteration":965,"passed_time":18.71508902,"remaining_time":0.6587091375},
{"learn":[0.1529562657],"iteration":966,"passed_time":18.74200539,"remaining_time":0.6395927384},
{"learn":[0.1529264298],"iteration":967,"passed_time":18.75953706,"remaining_time":0.6201499853},
{"learn":[0.1529013682],"iteration":968,"passed_time":18.79282014,"remaining_time":0.6012150921},
{"learn":[0.1528406741],"iteration":969,"passed_time":18.81876451,"remaining_time":0.5820236447},
{"learn":[0.1527751108],"iteration":970,"passed_time":18.85501687,"remaining_time":0.5631261475},
{"learn":[0.1527453158],"iteration":971,"passed_time":18.8709686,"remaining_time":0.5436081489},
{"learn":[0.1527311533],"iteration":972,"passed_time":18.88765686,"remaining_time":0.5241179191},
{"learn":[0.1526746143],"iteration":973,"passed_time":18.92474676,"remaining_time":0.5051780449},
{"learn":[0.1526382736],"iteration":974,"passed_time":18.93894657,"remaining_time":0.4856140145},
{"learn":[0.1525970195],"iteration":975,"passed_time":18.95309012,"remaining_time":0.4660595931},
{"learn":[0.1525524247],"iteration":976,"passed_time":18.98670812,"remaining_time":0.4469747051},
{"learn":[0.1525123499],"iteration":977,"passed_time":19.00316644,"remaining_time":0.4274740918},
{"learn":[0.1524900264],"iteration":978,"passed_time":19.03678466,"remaining_time":0.4083477812},
{"learn":[0.152438317],"iteration":979,"passed_time":19.05560634,"remaining_time":0.3888899253},
{"learn":[0.1524156043],"iteration":980,"passed_time":19.07134295,"remaining_time":0.3693736147},
{"learn":[0.1524043243],"iteration":981,"passed_time":19.10177282,"remaining_time":0.3501343287},
{"learn":[0.152375857],"iteration":982,"passed_time":19.13264419,"remaining_time":0.3308799097},
{"learn":[0.1523533698],"iteration":983,"passed_time":19.150622,"remaining_time":0.3113922277},
{"learn":[0.1523365256],"iteration":984,"passed_time":19.16778306,"remaining_time":0.2918951736},
{"learn":[0.1522888231],"iteration":985,"passed_time":19.19683912,"remaining_time":0.2725717523},
{"learn":[0.152265257],"iteration":986,"passed_time":19.2241253,"remaining_time":0.2532052977},
{"learn":[0.1522335823],"iteration":987,"passed_time":19.24967656,"remaining_time":0.2338017396},
{"learn":[0.1522194462],"iteration":988,"passed_time":19.27243711,"remaining_time":0.21435471},
{"learn":[0.1521692884],"iteration":989,"passed_time":19.29603239,"remaining_time":0.194909418},
{"learn":[0.1520802168],"iteration":990,"passed_time":19.31983565,"remaining_time":0.1754576396},
{"learn":[0.1520419269],"iteration":991,"passed_time":19.34653136,"remaining_time":0.1560204142},
{"learn":[0.1520234482],"iteration":992,"passed_time":19.36607143,"remaining_time":0.1365181269},
{"learn":[0.1519992483],"iteration":993,"passed_time":19.3818414,"remaining_time":0.1169930064},
{"learn":[0.1519558037],"iteration":994,"passed_time":19.41107922,"remaining_time":0.09754311166},
{"learn":[0.1519092327],"iteration":995,"passed_time":19.44021289,"remaining_time":0.07807314416},
{"learn":[0.151892822],"iteration":996,"passed_time":19.46549991,"remaining_time":0.05857221639},
{"learn":[0.1518619887],"iteration":997,"passed_time":19.47889022,"remaining_time":0.03903585214},
{"learn":[0.1517898447],"iteration":998,"passed_time":19.50809288,"remaining_time":0.0195276205},
{"learn":[0.151741416],"iteration":999,"passed_time":19.52731727,"remaining_time":0}
]}